Workbook

Sheet Events
A1: date | B1: country/bloc | C1: Acquiescence (0/1) | D1: Adaptation (0/1) | E1: Aggregation (0/1) | F1: OTHER (0/1) | G1: other_type | H1: source outlet | I1: source URL | J1: headline | K1: us_trigger | L1: action description | M1: key quote supporting categorization | N1: classification_confidence | O1: Interim_result_type | P1: Interim_results | Q1: Interim_result_source_URL
A2: 40210 | B2: Vietnam | C2: 0 | D2: 0 | E2: 0 | F2: 1 | G2: WTO_challenge | H2: WTO | I2: https://www.wto.org/english/tratop_e/dispu_e/cases_e/ds404_e.htm | J2: Vietnam challenges US shrimp anti-dumping measures | K2: US anti-dumping duties / zeroing on Vietnamese shrimp | L2: Vietnam requested WTO consultations over US anti-dumping reviews and zeroing practices. This is direct legal contestation, not one of the 3As. | M2: Viet Nam requested consultations with the United States concerning a number of anti-dumping measures | N2: High | O2: US_holds_position | P2: No clear US relief followed within 60 days; the dispute proceeded through WTO litigation while the US anti-dumping measures remained in place. | Q2: https://www.wto.org/english/tratop_e/dispu_e/cases_e/ds404_e.htm
A3: 40515 | B3: South Korea | C3: 1 | D3: 0 | E3: 0 | F3: 0 | H3: US Department of State | I3: https://2009-2017.state.gov/e/eb/rls/rm/2011/166630.htm | J3: Korea accepts revised KORUS auto package | K3: US refusal to ratify original KORUS over auto market-access concerns | L3: Seoul accepted revised auto-market terms to address named US objections and unlock US ratification. | M3: Korea will immediately cut in half its tariffs on U.S. automotive exports | N3: High | O3: no_clear_result_within_60d | P3: The revised KORUS package resolved the immediate bilateral negotiating impasse, but US congressional approval/implementation did not occur within 60 days. | Q3: https://2009-2017.state.gov/e/eb/rls/rm/2011/166630.htm
A4: 40515 | B4: South Korea | C4: 1 | D4: 0 | E4: 0 | F4: 0 | H4: US Department of State | I4: https://2009-2017.state.gov/e/eb/rls/rm/2011/166630.htm | J4: Korea relaxes auto safety and environmental barriers | K4: US KORUS auto market-access demands | L4: The revised KORUS package addressed Korean safety and environmental standards that Washington said impeded US auto exports. | M4: addressing ways Korea’s system of automotive safety standards have served as barriers | N4: High | O4: no_clear_result_within_60d | P4: The revised KORUS package resolved the immediate bilateral negotiating impasse, but US congressional approval/implementation did not occur within 60 days. | Q4: https://2009-2017.state.gov/e/eb/rls/rm/2011/166630.htm
A5: 40896 | B5: Japan | C5: 1 | D5: 0 | E5: 0 | F5: 0 | H5: USTR | I5: https://www.ustr.gov/about-us/policy-offices/press-office/press-releases/2011/december/us-trade-representative-ron-kirk-japanese-ministe | J5: Japan launches review of US beef restrictions | K5: Longstanding US demand for wider beef-market access | L5: Japan launched a risk-assessment process to reassess import restrictions after sustained US pressure. | M5: reassess import restrictions through the launch of a risk assessment process | N5: High | O5: implementation/monitoring | P5: The review process continued; no discrete US concession or escalation attributable to Japan's review was identified within 60 days. | Q5: https://www.ustr.gov/about-us/policy-offices/press-office/press-releases/2011/december/us-trade-representative-ron-kirk-japanese-ministe
A6: 40955 | B6: Vietnam | C6: 0 | D6: 0 | E6: 0 | F6: 1 | G6: WTO_challenge | H6: USTR | I6: https://ustr.gov/node/1458 | J6: Vietnam launches second WTO challenge to US shrimp duties | K6: US anti-dumping measures on frozen warmwater shrimp | L6: Vietnam again requested WTO consultations over US anti-dumping reviews and related practices. | M6: Viet Nam requested consultations with the United States concerning a number of anti-dumping measures | N6: High | O6: US_holds_position | P6: The United States defended its measures and the dispute proceeded to a WTO panel rather than producing near-term relief. | Q6: https://www.wto.org/english/news_e/news13_e/dsb_18feb13_e.htm
A7: 41376 | B7: Japan | C7: 1 | D7: 0 | E7: 0 | F7: 0 | H7: USTR | I7: https://ustr.gov/about-us/policy-offices/press-office/fact-sheets/2013/april/US-consultations-Japan | J7: Japan expands simplified certification for US autos | K7: US conditions for supporting Japan entry into TPP negotiations | L7: Japan more than doubled the number of vehicles per type eligible for its simplified Preferential Handling Procedure. | M7: more than double the number of motor vehicles eligible for import under its Preferential Handling Procedure | N7: High | O7: US_concedes/relaxes | P7: The United States completed bilateral consultations, endorsed Japan's TPP participation and notified Congress of its intent to include Japan in the negotiations. | Q7: https://ustr.gov/about-us/policy-offices/press-office/press-releases/2013/april/congressional-notification-japan-tpp
A8: 41376 | B8: Japan | C8: 1 | D8: 0 | E8: 0 | F8: 0 | H8: USTR | I8: https://ustr.gov/about-us/policy-offices/press-office/fact-sheets/2013/april/US-consultations-Japan | J8: Japan accepts parallel auto non-tariff negotiations | K8: US conditions for Japan TPP entry | L8: Japan accepted bilateral negotiations on a broad range of auto non-tariff barriers alongside TPP. | M8: agreed to address a broad range of non-tariff measures in Japan’s automotive sector | N8: High | O8: US_concedes/relaxes | P8: The United States completed bilateral consultations, endorsed Japan's TPP participation and notified Congress of its intent to include Japan in the negotiations. | Q8: https://ustr.gov/about-us/policy-offices/press-office/press-releases/2013/april/congressional-notification-japan-tpp
A9: 41376 | B9: Japan | C9: 1 | D9: 0 | E9: 0 | F9: 0 | H9: USTR | I9: https://ustr.gov/about-us/policy-offices/press-office/fact-sheets/2013/april/US-consultations-Japan | J9: Japan freezes new Japan Post insurance products | K9: US insurance-market level-playing-field demand tied to TPP entry | L9: Japan agreed not to approve specified new Japan Post insurance products until competitive conditions improved. | M9: refrain from approving new or modified cancer insurance and/or stand-alone medical products | N9: High | O9: US_concedes/relaxes | P9: The United States completed bilateral consultations, endorsed Japan's TPP participation and notified Congress of its intent to include Japan in the negotiations. | Q9: https://ustr.gov/about-us/policy-offices/press-office/press-releases/2013/april/congressional-notification-japan-tpp
A10: 41466 | B10: India | C10: 1 | D10: 0 | E10: 0 | F10: 0 | H10: USTR | I10: https://ustr.gov/about-us/policy-offices/press-office/press-releases/2013/july/readout-froman-sharma | J10: India removes private-sector electronics local-purchase mandate | K10: US objections to Preferential Market Access localization requirements | L10: India committed to modify PMA so private electronics procurement would no longer face domestic-manufacturing mandates. | M10: revised policy would not have domestic manufacturing requirements...with respect to private sector procurement | N10: High | O10: implementation/monitoring | P10: USTR welcomed India's commitment to remove private-sector localization requirements but explicitly maintained concern about other localization barriers. | Q10: https://ustr.gov/about-us/policy-offices/press-office/press-releases/2013/july/readout-froman-sharma
A11: 41347 | B11: Indonesia | C11: 0 | D11: 0 | E11: 0 | F11: 1 | G11: legal_defense | H11: USTR | I11: https://www.ustr.gov/about-us/policy-offices/press-office/press-releases/2013/march/ustr-kirk-wto-dispute-indonesia | J11: Indonesia maintains import restrictions after US consultations | K11: US WTO challenge to horticultural and animal-product import restrictions | L11: US consultations failed to resolve the dispute and Indonesia maintained/revised restrictive measures; this is resistance/non-concession rather than a 3A. | M11: consultations did not resolve the concerns | N11: Med | O11: US_escalates | P11: The United States requested establishment of a WTO dispute-settlement panel, moving the dispute beyond consultations. | Q11: https://ustr.gov/about-us/policy-offices/press-office/press-releases/2013/march/ustr-kirk-wto-dispute-indonesia
A12: 41757 | B12: Philippines | C12: 1 | D12: 0 | E12: 0 | F12: 0 | H12: USTR | I12: https://ustr.gov/about-us/policy-offices/press-office/press-releases/2014/April/US-Removes-the-Philippines-from-the-Special-301-Watch-List | J12: Philippines reforms IP regime and leaves Special 301 Watch List | K12: US Special 301 intellectual-property pressure | L12: After years of US Special 301 scrutiny, the Philippines enacted legislative/regulatory reforms and improved enforcement sufficiently for removal from the Watch List. | M12: enacted a series of significant legislative and regulatory reforms | N12: High | O12: US_concedes/relaxes | P12: USTR removed the Philippines from the Special 301 Watch List while stating that engagement on remaining IP issues would continue. | Q12: https://ustr.gov/about-us/policy-offices/press-office/press-releases/2014/April/US-Removes-the-Philippines-from-the-Special-301-Watch-List
A13: 41757 | B13: Philippines | C13: 1 | D13: 0 | E13: 0 | F13: 0 | H13: Obama White House | I13: https://obamawhitehouse.archives.gov/the-press-office/2014/04/28/fact-sheet-united-states-philippines-bilateral-relations | J13: Philippines agrees agricultural market-access package | K13: US support sought for special WTO treatment of Philippine rice restrictions | L13: Manila agreed market-access steps facilitating US agricultural exports in exchange for US support for its WTO rice request. | M13: Agreement in principle on the general market access terms, including steps to facilitate trade by the Philippines | N13: High | O13: US_concedes/relaxes | P13: The United States agreed in principle to support special WTO treatment for Philippine rice restrictions after the market-access package. | Q13: https://obamawhitehouse.archives.gov/the-press-office/2014/04/28/fact-sheet-united-states-philippines-bilateral-relations
A14: 42198 | B14: India | C14: 1 | D14: 0 | E14: 0 | F14: 0 | H14: WTO | I14: https://www.wto.org/english/tratop_e/dispu_e/cases_e/ds430_e.htm | J14: India commits to implement poultry ruling | K14: US WTO challenge to Indian poultry restrictions | L14: After losing the dispute, India told the DSB it intended to implement the ruling and requested time to comply. | M14: intended to implement the DSB’s recommendations and rulings | N14: High | O14: implementation/monitoring | P14: The United States accepted a negotiated implementation period rather than immediate retaliation; the parties later agreed on a 12-month reasonable period for compliance. | Q14: https://www.wto.org/english/tratop_e/dispu_e/cases_e/ds430_e.htm
A15: 42333 | B15: Philippines | C15: 1 | D15: 0 | E15: 0 | F15: 0 | H15: USTR | I15: https://ustr.gov/about-us/policy-offices/press-office/press-releases/2015/november/ustr-uses-trade-preference | J15: US closes Philippines GSP worker-rights review after reforms | K15: US GSP worker-rights eligibility review | L15: The Philippines reformed labor laws and regulations sufficiently for USTR to close its longstanding GSP review. | M15: progress...including through reforms of labor laws and regulations | N15: High | O15: US_concedes/relaxes | P15: USTR closed the Philippines GSP worker-rights review with no loss of GSP benefits, citing reform progress. | Q15: https://ustr.gov/about-us/policy-offices/press-office/press-releases/2015/november/ustr-uses-trade-preference
A16: 42480 | B16: Thailand | C16: 1 | D16: 0 | E16: 0 | F16: 0 | H16: USTR | I16: https://ustr.gov/about-us/policy-offices/press-office/press-releases/2016/april/united-states-and-thailand-reaffirm | J16: Thailand agrees IP action plan with US | K16: US bilateral/Special 301 intellectual-property concerns | L16: Thailand agreed with US officials to finalize an IP action plan with benchmarks addressing named concerns. | M16: agreed to finalize an action plan...focusing on key concerns and benchmarks for progress | N16: High | O16: US_holds_position | P16: USTR's 2016 Special 301 process continued to identify Thailand's IP regime as an area of concern; no clear US relaxation was identified within 60 days. | Q16: https://ustr.gov/about-us/policy-offices/press-office/press-releases/2016/april/ustr-releases-special-301-report
A17: 42569 | B17: India | C17: 1 | D17: 0 | E17: 0 | F17: 0 | H17: WTO | I17: https://www.wto.org/english/tratop_e/dispu_e/cases_e/ds430_e.htm | J17: India changes poultry import rules to comply with WTO ruling | K17: US WTO poultry dispute and threatened suspension of concessions | L17: India notified new rules allowing imports from disease-free countries/zones in response to the adverse ruling. | M17: adopted the necessary measures to comply | N17: High | O17: US_holds_position | P17: The United States maintained that India had not complied and preserved its request to suspend concessions; the dispute moved into compliance/retaliation procedures. | Q17: https://www.wto.org/english/news_e/news16_e/dsb_19jul16_e.htm
A18: 42635 | B18: India | C18: 1 | D18: 0 | E18: 0 | F18: 0 | H18: WTO | I18: https://www.wto.org/english/tratop_e/dispu_e/cases_e/ds430_e.htm | J18: India adopts additional poultry measures after US concerns | K18: US bilateral concerns over India’s initial WTO compliance measures | L18: India adopted additional measures specifically to address concerns the United States expressed bilaterally. | M18: adopted additional measures to address concerns bilaterally expressed by the United States | N18: High | O18: implementation/monitoring | P18: The additional measures became part of the continuing WTO compliance process; no discrete US relaxation within 60 days was identified. | Q18: https://www.wto.org/english/tratop_e/dispu_e/cases_e/ds430_e.htm
A19: 42424 | B19: India | C19: 0 | D19: 0 | E19: 0 | F19: 1 | G19: WTO_litigation | H19: USTR | I19: https://www.ustr.gov/about-us/policy-offices/press-office/press-releases/2016/february/united-states-prevails-wto-dispute | J19: India defends solar domestic-content rules in WTO case | K19: US WTO challenge to Indian solar localization rules | L19: India defended its domestic-content requirements against the US challenge; the panel rejected its defenses. | M19: Panel rejected India’s defensive arguments | N19: High | O19: US_holds_position | P19: The United States prevailed before the WTO panel; India's defence did not produce near-term US withdrawal of the challenge. | Q19: https://www.ustr.gov/about-us/policy-offices/press-office/press-releases/2016/february/united-states-prevails-wto-dispute
A20: 42480 | B20: India | C20: 0 | D20: 0 | E20: 0 | F20: 1 | G20: WTO_appeal | H20: USITC | I20: https://www.usitc.gov/publications/332/otap2016.html | J20: India appeals adverse solar-content ruling | K20: US WTO challenge to Indian solar domestic-content rules | L20: India appealed the WTO panel decision rather than immediately conceding. | M20: India appealed the decision to the WTO Appellate Body | N20: High | O20: US_holds_position | P20: The United States continued to defend the adverse WTO ruling through India's appeal; no near-term US concession followed. | Q20: https://www.wto.org/english/tratop_e/dispu_e/cases_e/ds456_e.htm
A21: 42404 | B21: Malaysia | C21: 1 | D21: 0 | E21: 0 | F21: 0 | H21: Malaysia MITI | I21: https://www.miti.gov.my/index.php/pages/view/3150 | J21: Malaysia prepares legal reforms to implement TPP | K21: TPP obligations negotiated in US-anchored trade agreement | L21: Malaysia established an implementation structure and prepared amendments in rules of origin, IP and labour to meet negotiated TPP obligations. | M21: several laws will be amended...to meet the obligations stipulated under the TPPA | N21: Med | O21: implementation/monitoring | P21: TPP was signed on 4 February 2016 and implementation shifted to domestic ratification; no separate US concession within 60 days followed Malaysia's reform preparations. | Q21: https://ustr.gov/about-us/policy-offices/press-office/press-releases/2016/February/TPP-Ministers-Statement
A22: 42491 | B22: Vietnam | C22: 1 | D22: 0 | E22: 0 | F22: 0 | H22: USTR | I22: https://ustr.gov/about-us/policy-offices/press-office/fact-sheets/2016/may/fact-sheet-trans-pacific-partnership%E2%80%99s | J22: Vietnam commits to labor-law and institutional reforms under TPP | K22: US-Vietnam TPP labor plan / enforceable TPP conditions | L22: Vietnam undertook specific legal, regulatory and institutional commitments on labor rights under the US-Vietnam TPP labor plan. | M22: Implement legal, regulatory and institutional changes that strengthen the protection of all fundamental labor rights | N22: Med | O22: implementation/monitoring | P22: The labor reforms remained tied to prospective TPP implementation and US ratification; no discrete US relaxation within 60 days was identified. | Q22: https://ustr.gov/trade-agreements/free-trade-agreements/trans-pacific-partnership/tpp-full-text
A23: 42759 | B23: Japan | C23: 0 | D23: 0 | E23: 0 | F23: 1 | G23: refusal | H23: Japan Times | I23: https://www.japantimes.co.jp/news/2017/01/24/national/politics-diplomacy/tokyo-turns-down-australian-proposal-tpp-without-u-s-vows-keep-pushing-trump/ | J23: Japan initially rejects TPP without US | K23: US withdrawal from TPP | L23: Tokyo initially rejected Australia’s proposal to proceed without Washington and sought US return. | M23: TPP without the US was described as meaningless | N23: High | O23: no_clear_result_within_60d | P23: Japan continued trying to preserve the TPP framework; the decisive shift toward TPP-11 occurred later than the 60-day window. | Q23: https://www.mofa.go.jp/ecm/ep/page25e_000266.html
A24: 43123 | B24: CPTPP-11 | C24: 0 | D24: 0 | E24: 1 | F24: 0 | H24: Reuters / Investing.com | I24: https://www.investing.com/news/economy-news/tpp11-members-to-sign-transpacific-trade-pact-in-march-kyodo-1137578 | J24: TPP-11 agrees to sign CPTPP without United States | K24: US withdrawal from TPP | L24: The remaining 11 states institutionalised a successor trade pact without US participation. | M24: forge an Asia-Pacific trade pact after the United States pulled out | N24: High | O24: implementation/monitoring | P24: The eleven parties moved directly from agreement on the text to signing the CPTPP in March 2018; this was institutional follow-through rather than a US response. | Q24: https://geneva-wto.mfa.gov.sg/mission-updates/press-201801230-23-jan-2018/
A25: 43123 | B25: South Korea | C25: 0 | D25: 0 | E25: 0 | F25: 1 | G25: WTO_challenge | H25: Yonhap | I25: https://en.yna.co.kr/view/AEN20180123003651320 | J25: South Korea challenges US safeguard tariffs | K25: US safeguard tariffs on washers and solar panels | L25: Seoul announced a WTO challenge to the US safeguards. | M25: will file a petition with the World Trade Organization | N25: High | O25: US_holds_position | P25: The safeguard tariffs remained in force and Korea proceeded with WTO consultations; the United States did not withdraw the measure within 60 days. | Q25: https://www.wto.org/english/tratop_e/dispu_e/cases_e/ds546_e.htm
A26: 43169 | B26: Australia | C26: 1 | D26: 0 | E26: 0 | F26: 0 | H26: ABC News | I26: https://www.abc.net.au/news/2018-03-10/malcolm-turnbull-donald-trump-working-tariff-exemption-agreement/9534984 | J26: Australia negotiates Section 232 exemption | K26: US Section 232 steel/aluminium tariffs | L26: Canberra negotiated an exemption rather than retaliating, while stressing reciprocal security and trade ties. | M26: committed to having a very fair and reciprocal military and trade relationship | N26: Med | O26: US_concedes/relaxes | P26: The United States ultimately granted Australia a continuing exemption from the Section 232 steel tariff. | Q26: https://trumpwhitehouse.archives.gov/presidential-actions/presidential-proclamation-adjusting-imports-steel-united-states-3/
A27: 43160 | B27: South Korea | C27: 1 | D27: 0 | E27: 0 | F27: 0 | H27: USITC | I27: https://www.usitc.gov/publications/332/other/year_in_trade_2018_v3_0.html | J27: South Korea accepts steel quota | K27: US Section 232 steel tariff | L27: Seoul accepted an absolute annual quota in lieu of the 25% steel tariff. | M27: agreed to an absolute annual quota | N27: High | O27: compromise/mutual_settlement | P27: The United States exempted Korean steel from the 25% tariff but imposed a product-specific quota equal to 70% of recent import volume. | Q27: https://ustr.gov/about-us/policy-offices/press-office/fact-sheets/2018/march/new-us-trade-policy-and-national
A28: 43187 | B28: South Korea | C28: 1 | D28: 0 | E28: 0 | F28: 0 | H28: Trump White House | I28: https://trumpwhitehouse.archives.gov/briefings-statements/president-donald-j-trump-fulfilling-promise-united-states-korea-free-trade-agreement-national-security/ | J28: South Korea accepts currency-practice commitments | K28: US KORUS renegotiation / currency concerns | L28: Seoul committed to avoid competitive devaluation and improve foreign-exchange transparency. | M28: strong commitments on exchange rate practices, robust transparency, and reporting | N28: High | O28: implementation/monitoring | P28: The currency understanding was folded into the broader KORUS settlement with transparency and anti-devaluation commitments; US monitoring rather than further immediate pressure followed. | Q28: https://ustr.gov/about-us/policy-offices/press-office/fact-sheets/2018/march/new-us-trade-policy-and-national
A29: 43298 | B29: Japan/EU | C29: 0 | D29: 0 | E29: 1 | F29: 0 | H29: Reuters / Business Standard | I29: https://www.business-standard.com/article/reuters/japan-eu-sign-free-trade-pact-amid-worries-about-trump-policies-118071700702_1.html | J29: Japan and EU sign trade pact amid Trump protectionism | K29: Trump tariffs/protectionism | L29: Japan and the EU created a large non-US free-trade area framed as a counterweight to protectionism. | M29: counterweight to the protectionist forces unleashed by...Trump | N29: High | O29: US_holds_position | P29: No US tariff reversal followed the Japan-EU EPA within 60 days; Washington continued its protectionist trade agenda and bilateral pressure on Japan. | Q29: https://ustr.gov/about-us/policy-offices/press-office/press-releases/2018/september/joint-statement-united-states-and-japan
A30: 43632 | B30: India | C30: 0 | D30: 0 | E30: 0 | F30: 1 | G30: retaliation | H30: India PIB | I30: https://www.pib.gov.in/PressReleasePage.aspx?PRID=1576941&lang=2&reg=3 | J30: India imposes retaliatory tariffs on US products | K30: US Section 232 steel/aluminium tariffs | L30: India retaliated against 28 US products after delayed implementation of countermeasures. | M30: imposed retaliatory tariffs on 28 products | N30: High | O30: US_holds_position | P30: India's retaliation did not prompt removal of the US Section 232 steel/aluminium measures within 60 days. | Q30: https://ustr.gov/countries-regions/south-central-asia/india
A31: 44134 | B31: Indonesia | C31: 1 | D31: 0 | E31: 0 | F31: 0 | H31: USTR | I31: https://www.ustr.gov/about-us/policy-offices/press-office/press-releases/2020/october/ustr-announces-gsp-enforcement-action-country-successes-and-new-eligibility-reviews | J31: Indonesia reforms digital-trade policy under GSP review | K31: US GSP market-access review | L31: Indonesia changed digital-trade policies in response to US market-access concerns. | M31: specific reforms to Indonesia’s digital trade | N31: High | O31: US_concedes/relaxes | P31: USTR closed Indonesia's GSP market-access review with no loss of benefits, citing the reforms and continued implementation work. | Q31: https://www.ustr.gov/about-us/policy-offices/press-office/press-releases/2020/october/ustr-announces-gsp-enforcement-action-country-successes-and-new-eligibility-reviews
A32: 44134 | B32: Indonesia | C32: 1 | D32: 0 | E32: 0 | F32: 0 | H32: USTR | I32: https://www.ustr.gov/about-us/policy-offices/press-office/press-releases/2020/october/ustr-announces-gsp-enforcement-action-country-successes-and-new-eligibility-reviews | J32: Indonesia reforms insurance/reinsurance policy | K32: US GSP market-access review | L32: Indonesia made regulatory concessions addressing US insurance and reinsurance concerns. | M32: specific reforms to...insurance and reinsurance | N32: High | O32: US_concedes/relaxes | P32: USTR closed Indonesia's GSP market-access review with no loss of benefits, citing the reforms and continued implementation work. | Q32: https://www.ustr.gov/about-us/policy-offices/press-office/press-releases/2020/october/ustr-announces-gsp-enforcement-action-country-successes-and-new-eligibility-reviews
A33: 44134 | B33: Indonesia | C33: 1 | D33: 0 | E33: 0 | F33: 0 | H33: USTR | I33: https://www.ustr.gov/about-us/policy-offices/press-office/press-releases/2020/october/ustr-announces-gsp-enforcement-action-country-successes-and-new-eligibility-reviews | J33: Indonesia reforms agricultural import policy | K33: US GSP market-access review | L33: Jakarta changed agricultural-import policies as part of resolving the US review. | M33: specific reforms to...agricultural import policies | N33: High | O33: US_concedes/relaxes | P33: USTR closed Indonesia's GSP market-access review with no loss of benefits, citing the reforms and continued implementation work. | Q33: https://www.ustr.gov/about-us/policy-offices/press-office/press-releases/2020/october/ustr-announces-gsp-enforcement-action-country-successes-and-new-eligibility-reviews
A34: 44150 | B34: RCEP-15 | C34: 0 | D34: 0 | E34: 1 | F34: 0 | H34: ASEAN | I34: https://asean.org/joint-leaders-statement-on-the-regional-comprehensive-economic-partnership-rcep-3/ | J34: RCEP signed without United States | K34: Protectionism / fractured trading system; US absent | L34: Fifteen Asia-Pacific economies institutionalised a major non-US regional trade framework. | M34: open, inclusive, rules-based trade and investment arrangement | N34: Med | O34: no_clear_result_within_60d | P34: RCEP signature generated no discrete US policy concession within 60 days; the US remained outside the pact. | Q34: https://rcepsec.org/legal-text/
A35: 44396 | B35: Vietnam | C35: 1 | D35: 0 | E35: 0 | F35: 0 | H35: USTR | I35: https://ustr.gov/about-us/policy-offices/press-office/press-releases/2021/july/ambassador-katherine-tai-commends-treasury-department-and-state-bank-vietnam-reaching-agreement | J35: Vietnam commits to exchange-rate flexibility | K35: US Section 301 currency investigation / Treasury concerns | L35: The State Bank committed to greater exchange-rate flexibility after US currency pressure. | M35: continue to increase its exchange rate flexibility over time | N35: High | O35: US_concedes/relaxes | P35: Four days later USTR determined that the Treasury-SBV agreement satisfactorily resolved the Section 301 matter and that no trade action was warranted, subject to monitoring. | Q35: https://ustr.gov/about-us/policy-offices/press-office/press-releases/2021/july/ustr-releases-determination-action-and-ongoing-monitoring-following-us-vietnam-agreement-vietnams
A36: 44396 | B36: Vietnam | C36: 1 | D36: 0 | E36: 0 | F36: 0 | H36: USTR | I36: https://ustr.gov/about-us/policy-offices/press-office/press-releases/2021/july/ambassador-katherine-tai-commends-treasury-department-and-state-bank-vietnam-reaching-agreement | J36: Vietnam commits to FX transparency | K36: US Section 301 currency investigation | L36: Vietnam committed to greater disclosure of foreign-exchange intervention. | M36: providing information to Treasury with full transparency | N36: High | O36: US_concedes/relaxes | P36: Four days later USTR determined that the Treasury-SBV agreement satisfactorily resolved the Section 301 matter and that no trade action was warranted, subject to monitoring. | Q36: https://ustr.gov/about-us/policy-offices/press-office/press-releases/2021/july/ustr-releases-determination-action-and-ongoing-monitoring-following-us-vietnam-agreement-vietnams
A37: 44470 | B37: Vietnam | C37: 1 | D37: 0 | E37: 0 | F37: 0 | H37: USTR | I37: https://ustr.gov/about-us/policy-offices/press-office/press-releases/2021/october/ustr-announces-agreement-between-united-states-and-vietnam-resolve-timber-section-301-investigation | J37: Vietnam reforms timber-legality system | K37: US Section 301 timber investigation | L37: Vietnam committed to improve its Timber Legality Assurance System to resolve the investigation. | M37: commitments to improve its Timber Legality Assurance System | N37: High | O37: US_concedes/relaxes | P37: USTR declared the timber agreement a satisfactory resolution and said no Section 301 trade action was warranted, while retaining implementation monitoring. | Q37: https://ustr.gov/about-us/policy-offices/press-office/press-releases/2021/october/ustr-announces-agreement-between-united-states-and-vietnam-resolve-timber-section-301-investigation
A38: 45099 | B38: India | C38: 1 | D38: 0 | E38: 0 | F38: 0 | H38: USTR | I38: https://ustr.gov/about-us/policy-offices/press-office/press-releases/2023/june/united-states-announces-major-resolution-key-trade-issues-india | J38: India agrees to remove retaliatory Section 232 tariffs | K38: US Section 232 steel/aluminium dispute | L38: India agreed to remove retaliatory tariffs on specified US products as part of a broader resolution of bilateral trade disputes. | M38: India will remove the retaliatory tariffs | N38: High | O38: compromise/mutual_settlement | P38: The United States and India agreed to terminate six WTO disputes; India removed retaliatory tariffs, while the underlying US Section 232 regime was not generally withdrawn. | Q38: https://ustr.gov/about-us/policy-offices/press-office/press-releases/2023/june/united-states-announces-major-resolution-key-trade-issues-india
A39: 45016 | B39: Japan | C39: 1 | D39: 0 | E39: 0 | F39: 0 | H39: Japan METI | I39: https://www.meti.go.jp/english/speeches/press_conferences/2023/0331001.html | J39: Japan introduces semiconductor-equipment export controls | K39: US October 2022 semiconductor export controls | L39: Japan imposed controls after allied consultations, while denying it was merely following Washington. | M39: exchanging opinions with our allies...including the United States and the Netherlands | N39: Med | O39: implementation/monitoring | P39: Japan's controls proceeded as a coordinated export-control tightening; no US relaxation was at issue, and implementation rather than bilateral bargaining followed. | Q39: https://www.meti.go.jp/english/press/2023/0331_001.html
A40: 45701 | B40: India | C40: 1 | D40: 0 | E40: 0 | F40: 0 | H40: Reuters / Investing.com | I40: https://www.investing.com/news/commodities-news/indias-modi-brings-a-tariff-gift-to-trump-talks-3866437 | J40: India promises more US energy purchases | K40: Trump reciprocal-tariff pressure | L40: New Delhi pledged increased US oil and gas purchases while seeking relief from tariff pressure. | M40: promised to buy more U.S. oil, gas | N40: High | O40: US_holds_position | P40: The purchase pledge did not avert the April 2 reciprocal-tariff announcement; India was subsequently assigned a country-specific reciprocal tariff. | Q40: https://www.whitehouse.gov/presidential-actions/2025/04/regulating-imports-with-a-reciprocal-tariff-to-rectify-trade-practices-that-contribute-to-large-and-persistent-annual-united-states-goods-trade-deficits/
A41: 45744 | B41: India | C41: 1 | D41: 0 | E41: 0 | F41: 0 | H41: Reuters / ThePrint | I41: https://theprint.in/india/india-offers-us-tariff-cuts-on-farm-imports-eyes-trade-success-government-sources-say/2568891/ | J41: India offers tariff cuts on US farm goods | K41: Threatened Trump reciprocal tariffs | L41: India offered tariff reductions on selected US farm products. | M41: offered tariff cuts on imports of U.S. farm products | N41: High | O41: US_holds_position | P41: India's tariff-cut offer did not avert the April 2 reciprocal-tariff action; negotiations continued rather than producing immediate relief. | Q41: https://www.whitehouse.gov/presidential-actions/2025/04/regulating-imports-with-a-reciprocal-tariff-to-rectify-trade-practices-that-contribute-to-large-and-persistent-annual-united-states-goods-trade-deficits/
A42: 45750 | B42: Australia | C42: 0 | D42: 0 | E42: 0 | F42: 1 | G42: diplomatic_protest_nonretaliation | H42: Reuters / Investing.com | I42: https://www.investing.com/news/world-news/australia-says-us-tariffs-not-act-of-a-friend-but-rules-out-reciprocal-move-3964018 | J42: Australia condemns US tariff but rules out retaliation | K42: Trump 10% tariff | L42: Canberra publicly criticised the tariff while ruling out reciprocal retaliation. | M42: not the act of a friend | N42: High | O42: US_holds_position | P42: Australia's criticism and non-retaliation did not change the baseline 10% US tariff within 60 days. | Q42: https://www.dfat.gov.au/news/news/us-tariff-announcements
A43: 45755 | B43: Thailand | C43: 1 | D43: 0 | E43: 0 | F43: 0 | H43: Reuters / Investing.com | I43: https://www.investing.com/news/economy-news/thailand-to-increase-us-imports-lower-taxes-in-tariff-response-3973145 | J43: Thailand offers increased US imports | K43: Trump 36% reciprocal tariff | L43: Bangkok offered to increase US imports during negotiations over the threatened tariff. | M43: will increase U.S. imports | N43: High | O43: implementation/monitoring | P43: The United States paused the higher country-specific reciprocal tariffs during negotiations, but no final Thailand rate was settled within 60 days. | Q43: https://www.whitehouse.gov/presidential-actions/2025/04/modifying-reciprocal-tariff-rates-to-reflect-trading-partner-retaliation-and-alignment/
A44: 45755 | B44: Thailand | C44: 1 | D44: 0 | E44: 0 | F44: 0 | H44: Reuters / Investing.com | I44: https://www.investing.com/news/economy-news/thailand-to-increase-us-imports-lower-taxes-in-tariff-response-3973145 | J44: Thailand offers tariff reductions | K44: Trump 36% reciprocal tariff | L44: Thailand offered reductions in high tariffs on US goods. | M44: lower some of the higher taxes on American goods | N44: High | O44: implementation/monitoring | P44: The United States paused the higher country-specific reciprocal tariffs during negotiations, but no final Thailand rate was settled within 60 days. | Q44: https://www.whitehouse.gov/presidential-actions/2025/04/modifying-reciprocal-tariff-rates-to-reflect-trading-partner-retaliation-and-alignment/
A45: 45755 | B45: Singapore | C45: 0 | D45: 1 | E45: 0 | F45: 0 | H45: Singapore EDB | I45: https://www.edb.gov.sg/en/business-insights/insights/trump-tariffs-singapore-to-form-task-force-to-help-businesses-and-workers-says-pm-wong.html | J45: Singapore creates tariff-response task force | K45: Trump reciprocal/universal tariffs | L45: Singapore created a domestic government-business-labour task force to help firms and workers absorb tariff shocks. | M45: support businesses and workers | N45: High | O45: US_holds_position | P45: Singapore's resilience response did not alter the US baseline tariff; the tariff remained in place while Singapore focused on domestic cushioning. | Q45: https://www.mti.gov.sg/newsroom/singapore-economic-resilience-taskforce--sert--to-support-businesses-and-workers/
A46: 45756 | B46: South Korea | C46: 0 | D46: 1 | E46: 0 | F46: 0 | H46: Reuters / Investing.com | I46: https://www.investing.com/news/stock-market-news/south-korea-announces-emergency-measures-for-auto-industry-hit-by-us-tariffs-3975405 | J46: South Korea launches emergency auto-sector support | K46: US 25% auto tariff | L46: Seoul introduced financial support, tax measures and subsidies to strengthen the domestic automobile sector. | M46: emergency support measures for its auto sector | N46: High | O46: US_holds_position | P46: The 25% US auto tariff remained in force during the next two months; Korean auto exports to the US fell sharply in April. | Q46: https://en.yna.co.kr/view/AEN20250520002000320
A47: 45757 | B47: ASEAN | C47: 0 | D47: 0 | E47: 1 | F47: 0 | H47: ASEAN | I47: https://asean.org/joint-statement-of-the-asean-economic-ministers-on-the-introduction-of-unilateral-tariffs-of-the-united-states/ | J47: ASEAN adopts collective response to US tariffs | K47: Trump April 2 reciprocal tariffs | L47: ASEAN economic ministers coordinated a common regional response to the unilateral US tariffs. | M47: common intention | N47: High | O47: implementation/monitoring | P47: The United States had already announced a 90-day pause on the higher country-specific tariffs; ASEAN pursued dialogue, but Washington did not grant a bloc-wide settlement within 60 days. | Q47: https://asean.org/joint-statement-of-the-asean-economic-ministers-on-the-introduction-of-unilateral-tariffs-of-the-united-states/
A48: 45761 | B48: Thailand | C48: 1 | D48: 0 | E48: 0 | F48: 0 | H48: Reuters / Investing.com | I48: https://www.investing.com/news/economy-news/thailand-says-to-discuss-tariffs-with-united-states-on-april-21-3982751 | J48: Thailand promises stricter transshipment inspections | K48: Trump reciprocal tariffs / circumvention concerns | L48: Bangkok announced tighter inspections to prevent third countries from routing goods through Thailand to evade US duties. | M48: stricter inspections...to ensure other countries were not using Thailand to circumvent U.S. taxes | N48: High | O48: implementation/monitoring | P48: Thailand's anti-transshipment pledge fed into continuing bilateral negotiations; no final tariff settlement was reached within 60 days. | Q48: https://www.whitehouse.gov/presidential-actions/2025/04/modifying-reciprocal-tariff-rates-to-reflect-trading-partner-retaliation-and-alignment/
A49: 45763 | B49: Singapore | C49: 0 | D49: 1 | E49: 0 | F49: 0 | H49: Singapore MTI | I49: https://www.mti.gov.sg/newsroom/singapore-economic-resilience-taskforce--sert--to-support-businesses-and-workers/ | J49: Singapore launches Economic Resilience Taskforce | K49: Trump tariffs | L49: Singapore institutionalised a domestic resilience response to global tariff disruption. | M49: strengthen our resilience | N49: High | O49: US_holds_position | P49: Singapore's domestic resilience measures did not produce a change in the US baseline tariff within 60 days. | Q49: https://www.mti.gov.sg/newsroom/singapore-economic-resilience-taskforce--sert--to-support-businesses-and-workers/
A50: 45772 | B50: Japan | C50: 0 | D50: 1 | E50: 0 | F50: 0 | H50: Reuters / Investing.com | I50: https://www.investing.com/news/economy-news/japan-decides-on-economic-package-to-help-ease-tariff-pain-pm-ishiba-says-4003684 | J50: Japan adopts emergency tariff package | K50: Trump auto and reciprocal tariffs | L50: Tokyo expanded government-backed financing and other support to cushion tariff-exposed industries. | M50: emergency economic package to alleviate any impact | N50: High | O50: US_holds_position | P50: Japan-US negotiations continued, but by early May Tokyo reported that a gap remained and US auto-parts tariffs were taking effect; no relief had yet been secured. | Q50: https://japan.kantei.go.jp/103/statement/202505/03kaiken.html
A51: 45783 | B51: India/UK | C51: 0 | D51: 0 | E51: 1 | F51: 0 | H51: Reuters / Investing.com | I51: https://www.investing.com/news/world-news/britain-and-india-clinch-landmark-trade-deal-in-shadow-of-trumps-tariffs-4025079 | J51: India and UK conclude FTA amid tariff turmoil | K51: Trump global tariffs | L51: India and Britain concluded their bilateral FTA as US tariff turmoil strengthened incentives to diversify trade relationships. | M51: tariff turmoil sparked by U.S. | N51: High | O51: no_clear_result_within_60d | P51: The India-UK FTA was a diversification/aggregation move; no discrete US policy change attributable to it was identified within 60 days. | Q51: https://www.gov.uk/government/news/uk-india-trade-deal-concluded
A52: 45786 | B52: India | C52: 1 | D52: 0 | E52: 0 | F52: 0 | H52: Reuters / Investing.com | I52: https://www.investing.com/news/economic-indicators/exclusiveindia-offers-to-slash-tariff-gap-by-two-thirds-in-dash-to-seal-trade-pact-with-trump-4035573 | J52: India offers major tariff-gap reduction | K52: Trump tariff pressure | L52: New Delhi offered to sharply reduce its average tariff differential with the United States. | M52: slash its tariff gap...to less than 4% | N52: High | O52: implementation/monitoring | P52: US-India negotiations continued through the 60-day window without a final settlement; the offer did not itself produce immediate tariff relief. | Q52: https://ustr.gov/about-us/policy-offices/press-office/press-releases/2025/june/ustr-greer-meets-indian-commerce-and-industry-minister-goyal
A53: 45803 | B53: ASEAN | C53: 0 | D53: 0 | E53: 1 | F53: 0 | H53: ASEAN | I53: https://asean.org/asean-leaders-statement-on-responding-to-global-economic-and-trade-uncertainties/ | J53: ASEAN leaders coordinate response to tariff uncertainty | K53: Rising unilateral tariffs, principally US measures | L53: ASEAN leaders collectively instructed officials to monitor diversion and deepen regional economic resilience. | M53: strongest resolve to stand together as ASEAN | N53: High | O53: implementation/monitoring | P53: ASEAN's collective position was followed by continuing country-by-country negotiations with Washington rather than a bloc-wide US concession. | Q53: https://asean.org/asean-leaders-statement-on-responding-to-global-economic-and-trade-uncertainties/
A54: 45804 | B54: ASEAN | C54: 0 | D54: 0 | E54: 1 | F54: 0 | H54: Reuters / Investing.com | I54: https://www.investing.com/news/economic-indicators/asean-leaders-agree-tariff-deals-with-us-should-not-harm-members-4065028 | J54: ASEAN coordinates bilateral US tariff negotiations | K54: Trump reciprocal tariffs | L54: ASEAN governments agreed their individual bargains with Washington should not harm fellow members. | M54: should not be at the expense of any other country | N54: High | O54: implementation/monitoring | P54: Member states continued bilateral negotiations with Washington; no common ASEAN-US tariff settlement emerged within 60 days. | Q54: https://asean.org/asean-leaders-statement-on-responding-to-global-economic-and-trade-uncertainties/
... A67: 46055 | B67: India | C67: 1 | D67: 1 | E67: 0 | F67: 0 | H67: Reuters / Investing.com | I67: https://www.investing.com/news/world-news/trump-says-agreed-on-trade-deal-with-india-4479564 | J67: India agrees to halt Russian oil purchases | K67: US punitive tariff tied to Russian oil | L67: India agreed to change energy sourcing in direct response to a US tariff penalty, combining concession and domestic sourcing adjustment. | M67: Russian oil purchases | N67: Med | O67: US_concedes/relaxes | P67: The United States removed the additional 25% Russia-oil-related tariff in recognition of India's commitment to stop purchasing Russian oil. | Q67: https://www.whitehouse.gov/fact-sheets/2026/02/fact-sheet-the-united-states-and-india-announce-historic-trade-deal/
A68: 46098 | B68: Indonesia | C68: 0 | D68: 0 | E68: 0 | F68: 1 | G68: legal_defense | H68: Indonesia Coordinating Ministry for Economic Affairs | I68: https://www.ekon.go.id/publikasi/detail/6857/pemerintah-indonesia-antisipasi-investigasi-dari-ustr-dengan-persiapkan-argumentasi-dan-bukti-kuat | J68: Indonesia prepares defence against USTR overcapacity investigation | K68: US Section 301 structural excess-capacity investigation | L68: Jakarta prepared evidence and arguments to contest or answer the US investigation. | M68: argumentasi dan bukti kuat | N68: High | O68: implementation/monitoring | P68: The Section 301 investigation remained open through the two-month window, moving into written comments and May public hearings; no determination or tariff relief had yet been issued. | Q68: https://ustr.gov/trade-topics/enforcement/section-301-investigations/section-301-structural-excess-capacity-and-production-manufacturing-sectors
A69: 46101 | B69: South Korea | C69: 0 | D69: 1 | E69: 0 | F69: 0 | H69: Korean MOTIR | I69: https://english.motir.go.kr/eng/article/EATCLdfa319ada/2546/view | J69: South Korea launches Section 301 task force | K69: US Section 301 structural excess-capacity investigation | L69: Seoul created a domestic public-private mechanism to coordinate responses to US tariff and non-tariff risks. | M69: public-private joint task force on U.S. Section 301 matters | N69: High | O69: implementation/monitoring | P69: The Section 301 investigation remained open through the two-month window, moving into written comments and May public hearings; no determination had yet been issued. | Q69: https://ustr.gov/trade-topics/enforcement/section-301-investigations/section-301-structural-excess-capacity-and-production-manufacturing-sectors

Sheet Summary
A1: 3As responses to US trade policy — event dataset
A3: Metric | B3: Count | D3: Period | E3: Events | F3: Any 3A | G3: OTHER
A4: Events | B4: =COUNTA(Events!$A$2:$A$10000) -> 68 | D4: 2010–2016 | E4: =COUNTIFS(Events!$A$2:$A$10000,">="&DATE(2010,1,1),Events!$A$2:$A$10000,"<="&DATE(2016,12,31)) -> 21 | F4: =SUMPRODUCT(--(Events!$A$2:$A$10000>=DATE(2010,1,1)),--(Events!$A$2:$A$10000<=DATE(2016,12,31)),--((Events!$C$2:$C$10000+Events!$D$2:$D$10000+Events!$E$2:$E$10000)>0)) -> 16 | G4: =SUMIFS(Events!$F$2:$F$10000,Events!$A$2:$A$10000,">="&DATE(2010,1,1),Events!$A$2:$A$10000,"<="&DATE(2016,12,31)) -> 5
A5: Acquiescence | B5: =SUM(Events!$C$2:$C$10000) -> 44 | D5: 2017–2021 | E5: =COUNTIFS(Events!$A$2:$A$10000,">="&DATE(2017,1,1),Events!$A$2:$A$10000,"<="&DATE(2021,12,31)) -> 15 | F5: =SUMPRODUCT(--(Events!$A$2:$A$10000>=DATE(2017,1,1)),--(Events!$A$2:$A$10000<=DATE(2021,12,31)),--((Events!$C$2:$C$10000+Events!$D$2:$D$10000+Events!$E$2:$E$10000)>0)) -> 12 | G5: =SUMIFS(Events!$F$2:$F$10000,Events!$A$2:$A$10000,">="&DATE(2017,1,1),Events!$A$2:$A$10000,"<="&DATE(2021,12,31)) -> 3
A6: Adaptation | B6: =SUM(Events!$D$2:$D$10000) -> 8 | D6: 2022–2024 | E6: =COUNTIFS(Events!$A$2:$A$10000,">="&DATE(2022,1,1),Events!$A$2:$A$10000,"<="&DATE(2024,12,31)) -> 2 | F6: =SUMPRODUCT(--(Events!$A$2:$A$10000>=DATE(2022,1,1)),--(Events!$A$2:$A$10000<=DATE(2024,12,31)),--((Events!$C$2:$C$10000+Events!$D$2:$D$10000+Events!$E$2:$E$10000)>0)) -> 2 | G6: =SUMIFS(Events!$F$2:$F$10000,Events!$A$2:$A$10000,">="&DATE(2022,1,1),Events!$A$2:$A$10000,"<="&DATE(2024,12,31)) -> 0
A7: Aggregation | B7: =SUM(Events!$E$2:$E$10000) -> 9 | D7: 2025–2026 | E7: =COUNTIFS(Events!$A$2:$A$10000,">="&DATE(2025,1,1),Events!$A$2:$A$10000,"<="&DATE(2026,12,31)) -> 30 | F7: =SUMPRODUCT(--(Events!$A$2:$A$10000>=DATE(2025,1,1)),--(Events!$A$2:$A$10000<=DATE(2026,12,31)),--((Events!$C$2:$C$10000+Events!$D$2:$D$10000+Events!$E$2:$E$10000)>0)) -> 28 | G7: =SUMIFS(Events!$F$2:$F$10000,Events!$A$2:$A$10000,">="&DATE(2025,1,1),Events!$A$2:$A$10000,"<="&DATE(2026,12,31)) -> 2
A8: OTHER | B8: =SUM(Events!$F$2:$F$10000) -> 10
A9: Any 3A | B9: =SUMPRODUCT(--((Events!$C$2:$C$10000+Events!$D$2:$D$10000+Events!$E$2:$E$10000)>0)) -> 58
A12: OTHER types | D12: Source concentration (>3 events)
A13: WTO_challenge | B13: =COUNTIF(Events!$G$2:$G$10000,A13) -> 3 | D13: Reuters / Investing.com | E13: =COUNTIF(Events!$H$2:$H$10000,D13) -> 20
A14: legal_defense | B14: =COUNTIF(Events!$G$2:$G$10000,A14) -> 2 | D14: USTR | E14: =COUNTIF(Events!$H$2:$H$10000,D14) -> 19
A15: WTO_litigation | B15: =COUNTIF(Events!$G$2:$G$10000,A15) -> 1 | D15: ASEAN | E15: =COUNTIF(Events!$H$2:$H$10000,D15) -> 5
A16: WTO_appeal | B16: =COUNTIF(Events!$G$2:$G$10000,A16) -> 1 | D16: WTO | E16: =COUNTIF(Events!$H$2:$H$10000,D16) -> 4
A17: refusal | B17: =COUNTIF(Events!$G$2:$G$10000,A17) -> 1
A18: retaliation | B18: =COUNTIF(Events!$G$2:$G$10000,A18) -> 1
A19: diplomatic_protest_nonretaliation | B19: =COUNTIF(Events!$G$2:$G$10000,A19) -> 1

Sheet Coding Notes
A1: Item | B1: Rule / note
A2: Scope | B2: ASEAN member states plus Japan, South Korea, India and Australia; January 2010 to 2026-10-04.
A3: Acquiescence | B3: Visible concession on the specific axis of a named US contention, without public retaliation/pushback on that axis.
A4: Adaptation | B4: Domestic restructuring for resilience, not aimed directly at the US and not coordinated with other states.
A5: Aggregation | B5: Joint/plural coalition-building among non-US states framed as an alternative, complement or hedge to US-anchored arrangements.
A6: OTHER | B6: Observed response outside the 3As (e.g. retaliation, WTO challenge, refusal, diplomatic protest). OTHER is substantive, not uncertainty.
A7: Multiple coding | B7: An event may receive multiple positive binary codes when the action genuinely carries multiple messages.
A8: Confidence | B8: Confidence concerns evidence/classification quality; it is not a residual category.
A9: Event construction | B9: Substantively distinct actions within a single policy package are split; sequences such as challenge → compliance remain separate dated events.
A10: Source rule | B10: Every row contains a verifiable plain-text source URL. Official sources are used where contemporaneous news reporting is thin.
A11: Caution | B11: This is a fresh rebuild, not a splice of the earlier 42-row list. Search leads were stopped rather than padded with weak cases.
A14: Interim results coding (added 2026-10-05)
A15: Window | B15: Normally up to 60 days after the dated Asian response. The field records an observable interim disposition, not a claim about ultimate causal success.
A16: US_concedes/relaxes | B16: The US withdraws, lowers, suspends, exempts, or declines the challenged/ threatened action in a way favorable to the responding Third Nation.
A17: compromise/mutual_settlement | B17: Both sides make material moves; US relief is paired with significant Third-Nation concessions or the original US position remains partly intact.
A18: US_holds_position | B18: The US measure or demand remains materially in place through the window; the response does not obtain clear near-term relief.
A19: US_escalates | B19: The US intensifies the dispute or moves to a stronger enforcement/legal step after the response.
A20: implementation/monitoring | B20: The response produces or enters an implementation, negotiation, or monitoring phase without a clean US give-way/double-down outcome within the window.
A21: no_clear_result_within_60d | B21: No sufficiently attributable US disposition was found within the window; especially common for Aggregation or long-gestation institutional actions.
A22: Source caution | B22: Interim_result_source_URL records the principal source supporting the interim result. Absence of a US reaction is coded conservatively; the variable should not yet be read as a causal treatment-effect estimate.
A24: Annual Observations tab
A25: Annual category counts are formula-driven from Events. Pairwise columns are intersections: an event is counted only when both named category indicators equal 1. Counts are descriptive of the current exploratory event sample and should not be interpreted as shock-conditioned response rates or causal effects.

Sheet Monthly Timeline
A1: Month | B1: Total events | C1: Acquiescence | D1: Adaptation | E1: Aggregation | F1: OTHER | G1: Significant events / context
A2: 40179 | B2: =COUNTIFS(Events!$A$2:$A$10000,">="&A2,Events!$A$2:$A$10000,"<"&EDATE(A2,1)) -> 0 | C2: =SUMIFS(Events!$C$2:$C$10000,Events!$A$2:$A$10000,">="&A2,Events!$A$2:$A$10000,"<"&EDATE(A2,1)) -> 0 | D2: =SUMIFS(Events!$D$2:$D$10000,Events!$A$2:$A$10000,">="&A2,Events!$A$2:$A$10000,"<"&EDATE(A2,1)) -> 0 | E2: =SUMIFS(Events!$E$2:$E$10000,Events!$A$2:$A$10000,">="&A2,Events!$A$2:$A$10000,"<"&EDATE(A2,1)) -> 0 | F2: =SUMIFS(Events!$F$2:$F$10000,Events!$A$2:$A$10000,">="&A2,Events!$A$2:$A$10000,"<"&EDATE(A2,1)) -> 0
A3: 40210 | B3: =COUNTIFS(Events!$A$2:$A$10000,">="&A3,Events!$A$2:$A$10000,"<"&EDATE(A3,1)) -> 1 | C3: =SUMIFS(Events!$C$2:$C$10000,Events!$A$2:$A$10000,">="&A3,Events!$A$2:$A$10000,"<"&EDATE(A3,1)) -> 0 | D3: =SUMIFS(Events!$D$2:$D$10000,Events!$A$2:$A$10000,">="&A3,Events!$A$2:$A$10000,"<"&EDATE(A3,1)) -> 0 | E3: =SUMIFS(Events!$E$2:$E$10000,Events!$A$2:$A$10000,">="&A3,Events!$A$2:$A$10000,"<"&EDATE(A3,1)) -> 0 | F3: =SUMIFS(Events!$F$2:$F$10000,Events!$A$2:$A$10000,">="&A3,Events!$A$2:$A$10000,"<"&EDATE(A3,1)) -> 1
A4: 40238 | B4: =COUNTIFS(Events!$A$2:$A$10000,">="&A4,Events!$A$2:$A$10000,"<"&EDATE(A4,1)) -> 0 | C4: =SUMIFS(Events!$C$2:$C$10000,Events!$A$2:$A$10000,">="&A4,Events!$A$2:$A$10000,"<"&EDATE(A4,1)) -> 0 | D4: =SUMIFS(Events!$D$2:$D$10000,Events!$A$2:$A$10000,">="&A4,Events!$A$2:$A$10000,"<"&EDATE(A4,1)) -> 0 | E4: =SUMIFS(Events!$E$2:$E$10000,Events!$A$2:$A$10000,">="&A4,Events!$A$2:$A$10000,"<"&EDATE(A4,1)) -> 0 | F4: =SUMIFS(Events!$F$2:$F$10000,Events!$A$2:$A$10000,">="&A4,Events!$A$2:$A$10000,"<"&EDATE(A4,1)) -> 0
A5: 40269 | B5: =COUNTIFS(Events!$A$2:$A$10000,">="&A5,Events!$A$2:$A$10000,"<"&EDATE(A5,1)) -> 0 | C5: =SUMIFS(Events!$C$2:$C$10000,Events!$A$2:$A$10000,">="&A5,Events!$A$2:$A$10000,"<"&EDATE(A5,1)) -> 0 | D5: =SUMIFS(Events!$D$2:$D$10000,Events!$A$2:$A$10000,">="&A5,Events!$A$2:$A$10000,"<"&EDATE(A5,1)) -> 0 | E5: =SUMIFS(Events!$E$2:$E$10000,Events!$A$2:$A$10000,">="&A5,Events!$A$2:$A$10000,"<"&EDATE(A5,1)) -> 0 | F5: =SUMIFS(Events!$F$2:$F$10000,Events!$A$2:$A$10000,">="&A5,Events!$A$2:$A$10000,"<"&EDATE(A5,1)) -> 0
A6: 40299 | B6: =COUNTIFS(Events!$A$2:$A$10000,">="&A6,Events!$A$2:$A$10000,"<"&EDATE(A6,1)) -> 0 | C6: =SUMIFS(Events!$C$2:$C$10000,Events!$A$2:$A$10000,">="&A6,Events!$A$2:$A$10000,"<"&EDATE(A6,1)) -> 0 | D6: =SUMIFS(Events!$D$2:$D$10000,Events!$A$2:$A$10000,">="&A6,Events!$A$2:$A$10000,"<"&EDATE(A6,1)) -> 0 | E6: =SUMIFS(Events!$E$2:$E$10000,Events!$A$2:$A$10000,">="&A6,Events!$A$2:$A$10000,"<"&EDATE(A6,1)) -> 0 | F6: =SUMIFS(Events!$F$2:$F$10000,Events!$A$2:$A$10000,">="&A6,Events!$A$2:$A$10000,"<"&EDATE(A6,1)) -> 0
A7: 40330 | B7: =COUNTIFS(Events!$A$2:$A$10000,">="&A7,Events!$A$2:$A$10000,"<"&EDATE(A7,1)) -> 0 | C7: =SUMIFS(Events!$C$2:$C$10000,Events!$A$2:$A$10000,">="&A7,Events!$A$2:$A$10000,"<"&EDATE(A7,1)) -> 0 | D7: =SUMIFS(Events!$D$2:$D$10000,Events!$A$2:$A$10000,">="&A7,Events!$A$2:$A$10000,"<"&EDATE(A7,1)) -> 0 | E7: =SUMIFS(Events!$E$2:$E$10000,Events!$A$2:$A$10000,">="&A7,Events!$A$2:$A$10000,"<"&EDATE(A7,1)) -> 0 | F7: =SUMIFS(Events!$F$2:$F$10000,Events!$A$2:$A$10000,">="&A7,Events!$A$2:$A$10000,"<"&EDATE(A7,1)) -> 0
A8: 40360 | B8: =COUNTIFS(Events!$A$2:$A$10000,">="&A8,Events!$A$2:$A$10000,"<"&EDATE(A8,1)) -> 0 | C8: =SUMIFS(Events!$C$2:$C$10000,Events!$A$2:$A$10000,">="&A8,Events!$A$2:$A$10000,"<"&EDATE(A8,1)) -> 0 | D8: =SUMIFS(Events!$D$2:$D$10000,Events!$A$2:$A$10000,">="&A8,Events!$A$2:$A$10000,"<"&EDATE(A8,1)) -> 0 | E8: =SUMIFS(Events!$E$2:$E$10000,Events!$A$2:$A$10000,">="&A8,Events!$A$2:$A$10000,"<"&EDATE(A8,1)) -> 0 | F8: =SUMIFS(Events!$F$2:$F$10000,Events!$A$2:$A$10000,">="&A8,Events!$A$2:$A$10000,"<"&EDATE(A8,1)) -> 0
A9: 40391 | B9: =COUNTIFS(Events!$A$2:$A$10000,">="&A9,Events!$A$2:$A$10000,"<"&EDATE(A9,1)) -> 0 | C9: =SUMIFS(Events!$C$2:$C$10000,Events!$A$2:$A$10000,">="&A9,Events!$A$2:$A$10000,"<"&EDATE(A9,1)) -> 0 | D9: =SUMIFS(Events!$D$2:$D$10000,Events!$A$2:$A$10000,">="&A9,Events!$A$2:$A$10000,"<"&EDATE(A9,1)) -> 0 | E9: =SUMIFS(Events!$E$2:$E$10000,Events!$A$2:$A$10000,">="&A9,Events!$A$2:$A$10000,"<"&EDATE(A9,1)) -> 0 | F9: =SUMIFS(Events!$F$2:$F$10000,Events!$A$2:$A$10000,">="&A9,Events!$A$2:$A$10000,"<"&EDATE(A9,1)) -> 0
A10: 40422 | B10: =COUNTIFS(Events!$A$2:$A$10000,">="&A10,Events!$A$2:$A$10000,"<"&EDATE(A10,1)) -> 0 | C10: =SUMIFS(Events!$C$2:$C$10000,Events!$A$2:$A$10000,">="&A10,Events!$A$2:$A$10000,"<"&EDATE(A10,1)) -> 0 | D10: =SUMIFS(Events!$D$2:$D$10000,Events!$A$2:$A$10000,">="&A10,Events!$A$2:$A$10000,"<"&EDATE(A10,1)) -> 0 | E10: =SUMIFS(Events!$E$2:$E$10000,Events!$A$2:$A$10000,">="&A10,Events!$A$2:$A$10000,"<"&EDATE(A10,1)) -> 0 | F10: =SUMIFS(Events!$F$2:$F$10000,Events!$A$2:$A$10000,">="&A10,Events!$A$2:$A$10000,"<"&EDATE(A10,1)) -> 0
A11: 40452 | B11: =COUNTIFS(Events!$A$2:$A$10000,">="&A11,Events!$A$2:$A$10000,"<"&EDATE(A11,1)) -> 0 | C11: =SUMIFS(Events!$C$2:$C$10000,Events!$A$2:$A$10000,">="&A11,Events!$A$2:$A$10000,"<"&EDATE(A11,1)) -> 0 | D11: =SUMIFS(Events!$D$2:$D$10000,Events!$A$2:$A$10000,">="&A11,Events!$A$2:$A$10000,"<"&EDATE(A11,1)) -> 0 | E11: =SUMIFS(Events!$E$2:$E$10000,Events!$A$2:$A$10000,">="&A11,Events!$A$2:$A$10000,"<"&EDATE(A11,1)) -> 0 | F11: =SUMIFS(Events!$F$2:$F$10000,Events!$A$2:$A$10000,">="&A11,Events!$A$2:$A$10000,"<"&EDATE(A11,1)) -> 0
A12: 40483 | B12: =COUNTIFS(Events!$A$2:$A$10000,">="&A12,Events!$A$2:$A$10000,"<"&EDATE(A12,1)) -> 0 | C12: =SUMIFS(Events!$C$2:$C$10000,Events!$A$2:$A$10000,">="&A12,Events!$A$2:$A$10000,"<"&EDATE(A12,1)) -> 0 | D12: =SUMIFS(Events!$D$2:$D$10000,Events!$A$2:$A$10000,">="&A12,Events!$A$2:$A$10000,"<"&EDATE(A12,1)) -> 0 | E12: =SUMIFS(Events!$E$2:$E$10000,Events!$A$2:$A$10000,">="&A12,Events!$A$2:$A$10000,"<"&EDATE(A12,1)) -> 0 | F12: =SUMIFS(Events!$F$2:$F$10000,Events!$A$2:$A$10000,">="&A12,Events!$A$2:$A$10000,"<"&EDATE(A12,1)) -> 0
A13: 40513 | B13: =COUNTIFS(Events!$A$2:$A$10000,">="&A13,Events!$A$2:$A$10000,"<"&EDATE(A13,1)) -> 2 | C13: =SUMIFS(Events!$C$2:$C$10000,Events!$A$2:$A$10000,">="&A13,Events!$A$2:$A$10000,"<"&EDATE(A13,1)) -> 2 | D13: =SUMIFS(Events!$D$2:$D$10000,Events!$A$2:$A$10000,">="&A13,Events!$A$2:$A$10000,"<"&EDATE(A13,1)) -> 0 | E13: =SUMIFS(Events!$E$2:$E$10000,Events!$A$2:$A$10000,">="&A13,Events!$A$2:$A$10000,"<"&EDATE(A13,1)) -> 0 | F13: =SUMIFS(Events!$F$2:$F$10000,Events!$A$2:$A$10000,">="&A13,Events!$A$2:$A$10000,"<"&EDATE(A13,1)) -> 0 | G13: KORUS supplemental agreement announced (US–South Korea auto/trade concessions).
A14: 40544 | B14: =COUNTIFS(Events!$A$2:$A$10000,">="&A14,Events!$A$2:$A$10000,"<"&EDATE(A14,1)) -> 0 | C14: =SUMIFS(Events!$C$2:$C$10000,Events!$A$2:$A$10000,">="&A14,Events!$A$2:$A$10000,"<"&EDATE(A14,1)) -> 0 | D14: =SUMIFS(Events!$D$2:$D$10000,Events!$A$2:$A$10000,">="&A14,Events!$A$2:$A$10000,"<"&EDATE(A14,1)) -> 0 | E14: =SUMIFS(Events!$E$2:$E$10000,Events!$A$2:$A$10000,">="&A14,Events!$A$2:$A$10000,"<"&EDATE(A14,1)) -> 0 | F14: =SUMIFS(Events!$F$2:$F$10000,Events!$A$2:$A$10000,">="&A14,Events!$A$2:$A$10000,"<"&EDATE(A14,1)) -> 0
A15: 40575 | B15: =COUNTIFS(Events!$A$2:$A$10000,">="&A15,Events!$A$2:$A$10000,"<"&EDATE(A15,1)) -> 0 | C15: =SUMIFS(Events!$C$2:$C$10000,Events!$A$2:$A$10000,">="&A15,Events!$A$2:$A$10000,"<"&EDATE(A15,1)) -> 0 | D15: =SUMIFS(Events!$D$2:$D$10000,Events!$A$2:$A$10000,">="&A15,Events!$A$2:$A$10000,"<"&EDATE(A15,1)) -> 0 | E15: =SUMIFS(Events!$E$2:$E$10000,Events!$A$2:$A$10000,">="&A15,Events!$A$2:$A$10000,"<"&EDATE(A15,1)) -> 0 | F15: =SUMIFS(Events!$F$2:$F$10000,Events!$A$2:$A$10000,">="&A15,Events!$A$2:$A$10000,"<"&EDATE(A15,1)) -> 0
A16: 40603 | B16: =COUNTIFS(Events!$A$2:$A$10000,">="&A16,Events!$A$2:$A$10000,"<"&EDATE(A16,1)) -> 0 | C16: =SUMIFS(Events!$C$2:$C$10000,Events!$A$2:$A$10000,">="&A16,Events!$A$2:$A$10000,"<"&EDATE(A16,1)) -> 0 | D16: =SUMIFS(Events!$D$2:$D$10000,Events!$A$2:$A$10000,">="&A16,Events!$A$2:$A$10000,"<"&EDATE(A16,1)) -> 0 | E16: =SUMIFS(Events!$E$2:$E$10000,Events!$A$2:$A$10000,">="&A16,Events!$A$2:$A$10000,"<"&EDATE(A16,1)) -> 0 | F16: =SUMIFS(Events!$F$2:$F$10000,Events!$A$2:$A$10000,">="&A16,Events!$A$2:$A$10000,"<"&EDATE(A16,1)) -> 0
A17: 40634 | B17: =COUNTIFS(Events!$A$2:$A$10000,">="&A17,Events!$A$2:$A$10000,"<"&EDATE(A17,1)) -> 0 | C17: =SUMIFS(Events!$C$2:$C$10000,Events!$A$2:$A$10000,">="&A17,Events!$A$2:$A$10000,"<"&EDATE(A17,1)) -> 0 | D17: =SUMIFS(Events!$D$2:$D$10000,Events!$A$2:$A$10000,">="&A17,Events!$A$2:$A$10000,"<"&EDATE(A17,1)) -> 0 | E17: =SUMIFS(Events!$E$2:$E$10000,Events!$A$2:$A$10000,">="&A17,Events!$A$2:$A$10000,"<"&EDATE(A17,1)) -> 0 | F17: =SUMIFS(Events!$F$2:$F$10000,Events!$A$2:$A$10000,">="&A17,Events!$A$2:$A$10000,"<"&EDATE(A17,1)) -> 0
A18: 40664 | B18: =COUNTIFS(Events!$A$2:$A$10000,">="&A18,Events!$A$2:$A$10000,"<"&EDATE(A18,1)) -> 0 | C18: =SUMIFS(Events!$C$2:$C$10000,Events!$A$2:$A$10000,">="&A18,Events!$A$2:$A$10000,"<"&EDATE(A18,1)) -> 0 | D18: =SUMIFS(Events!$D$2:$D$10000,Events!$A$2:$A$10000,">="&A18,Events!$A$2:$A$10000,"<"&EDATE(A18,1)) -> 0 | E18: =SUMIFS(Events!$E$2:$E$10000,Events!$A$2:$A$10000,">="&A18,Events!$A$2:$A$10000,"<"&EDATE(A18,1)) -> 0 | F18: =SUMIFS(Events!$F$2:$F$10000,Events!$A$2:$A$10000,">="&A18,Events!$A$2:$A$10000,"<"&EDATE(A18,1)) -> 0
A19: 40695 | B19: =COUNTIFS(Events!$A$2:$A$10000,">="&A19,Events!$A$2:$A$10000,"<"&EDATE(A19,1)) -> 0 | C19: =SUMIFS(Events!$C$2:$C$10000,Events!$A$2:$A$10000,">="&A19,Events!$A$2:$A$10000,"<"&EDATE(A19,1)) -> 0 | D19: =SUMIFS(Events!$D$2:$D$10000,Events!$A$2:$A$10000,">="&A19,Events!$A$2:$A$10000,"<"&EDATE(A19,1)) -> 0 | E19: =SUMIFS(Events!$E$2:$E$10000,Events!$A$2:$A$10000,">="&A19,Events!$A$2:$A$10000,"<"&EDATE(A19,1)) -> 0 | F19: =SUMIFS(Events!$F$2:$F$10000,Events!$A$2:$A$10000,">="&A19,Events!$A$2:$A$10000,"<"&EDATE(A19,1)) -> 0
A20: 40725 | B20: =COUNTIFS(Events!$A$2:$A$10000,">="&A20,Events!$A$2:$A$10000,"<"&EDATE(A20,1)) -> 0 | C20: =SUMIFS(Events!$C$2:$C$10000,Events!$A$2:$A$10000,">="&A20,Events!$A$2:$A$10000,"<"&EDATE(A20,1)) -> 0 | D20: =SUMIFS(Events!$D$2:$D$10000,Events!$A$2:$A$10000,">="&A20,Events!$A$2:$A$10000,"<"&EDATE(A20,1)) -> 0 | E20: =SUMIFS(Events!$E$2:$E$10000,Events!$A$2:$A$10000,">="&A20,Events!$A$2:$A$10000,"<"&EDATE(A20,1)) -> 0 | F20: =SUMIFS(Events!$F$2:$F$10000,Events!$A$2:$A$10000,">="&A20,Events!$A$2:$A$10000,"<"&EDATE(A20,1)) -> 0
A21: 40756 | B21: =COUNTIFS(Events!$A$2:$A$10000,">="&A21,Events!$A$2:$A$10000,"<"&EDATE(A21,1)) -> 0 | C21: =SUMIFS(Events!$C$2:$C$10000,Events!$A$2:$A$10000,">="&A21,Events!$A$2:$A$10000,"<"&EDATE(A21,1)) -> 0 | D21: =SUMIFS(Events!$D$2:$D$10000,Events!$A$2:$A$10000,">="&A21,Events!$A$2:$A$10000,"<"&EDATE(A21,1)) -> 0 | E21: =SUMIFS(Events!$E$2:$E$10000,Events!$A$2:$A$10000,">="&A21,Events!$A$2:$A$10000,"<"&EDATE(A21,1)) -> 0 | F21: =SUMIFS(Events!$F$2:$F$10000,Events!$A$2:$A$10000,">="&A21,Events!$A$2:$A$10000,"<"&EDATE(A21,1)) -> 0
A22: 40787 | B22: =COUNTIFS(Events!$A$2:$A$10000,">="&A22,Events!$A$2:$A$10000,"<"&EDATE(A22,1)) -> 0 | C22: =SUMIFS(Events!$C$2:$C$10000,Events!$A$2:$A$10000,">="&A22,Events!$A$2:$A$10000,"<"&EDATE(A22,1)) -> 0 | D22: =SUMIFS(Events!$D$2:$D$10000,Events!$A$2:$A$10000,">="&A22,Events!$A$2:$A$10000,"<"&EDATE(A22,1)) -> 0 | E22: =SUMIFS(Events!$E$2:$E$10000,Events!$A$2:$A$10000,">="&A22,Events!$A$2:$A$10000,"<"&EDATE(A22,1)) -> 0 | F22: =SUMIFS(Events!$F$2:$F$10000,Events!$A$2:$A$10000,">="&A22,Events!$A$2:$A$10000,"<"&EDATE(A22,1)) -> 0
A23: 40817 | B23: =COUNTIFS(Events!$A$2:$A$10000,">="&A23,Events!$A$2:$A$10000,"<"&EDATE(A23,1)) -> 0 | C23: =SUMIFS(Events!$C$2:$C$10000,Events!$A$2:$A$10000,">="&A23,Events!$A$2:$A$10000,"<"&EDATE(A23,1)) -> 0 | D23: =SUMIFS(Events!$D$2:$D$10000,Events!$A$2:$A$10000,">="&A23,Events!$A$2:$A$10000,"<"&EDATE(A23,1)) -> 0 | E23: =SUMIFS(Events!$E$2:$E$10000,Events!$A$2:$A$10000,">="&A23,Events!$A$2:$A$10000,"<"&EDATE(A23,1)) -> 0 | F23: =SUMIFS(Events!$F$2:$F$10000,Events!$A$2:$A$10000,">="&A23,Events!$A$2:$A$10000,"<"&EDATE(A23,1)) -> 0
A24: 40848 | B24: =COUNTIFS(Events!$A$2:$A$10000,">="&A24,Events!$A$2:$A$10000,"<"&EDATE(A24,1)) -> 0 | C24: =SUMIFS(Events!$C$2:$C$10000,Events!$A$2:$A$10000,">="&A24,Events!$A$2:$A$10000,"<"&EDATE(A24,1)) -> 0 | D24: =SUMIFS(Events!$D$2:$D$10000,Events!$A$2:$A$10000,">="&A24,Events!$A$2:$A$10000,"<"&EDATE(A24,1)) -> 0 | E24: =SUMIFS(Events!$E$2:$E$10000,Events!$A$2:$A$10000,">="&A24,Events!$A$2:$A$10000,"<"&EDATE(A24,1)) -> 0 | F24: =SUMIFS(Events!$F$2:$F$10000,Events!$A$2:$A$10000,">="&A24,Events!$A$2:$A$10000,"<"&EDATE(A24,1)) -> 0
A25: 40878 | B25: =COUNTIFS(Events!$A$2:$A$10000,">="&A25,Events!$A$2:$A$10000,"<"&EDATE(A25,1)) -> 1 | C25: =SUMIFS(Events!$C$2:$C$10000,Events!$A$2:$A$10000,">="&A25,Events!$A$2:$A$10000,"<"&EDATE(A25,1)) -> 1 | D25: =SUMIFS(Events!$D$2:$D$10000,Events!$A$2:$A$10000,">="&A25,Events!$A$2:$A$10000,"<"&EDATE(A25,1)) -> 0 | E25: =SUMIFS(Events!$E$2:$E$10000,Events!$A$2:$A$10000,">="&A25,Events!$A$2:$A$10000,"<"&EDATE(A25,1)) -> 0 | F25: =SUMIFS(Events!$F$2:$F$10000,Events!$A$2:$A$10000,">="&A25,Events!$A$2:$A$10000,"<"&EDATE(A25,1)) -> 0
... A70: 42248 | B70: =COUNTIFS(Events!$A$2:$A$10000,">="&A70,Events!$A$2:$A$10000,"<"&EDATE(A70,1)) -> 0 | C70: =SUMIFS(Events!$C$2:$C$10000,Events!$A$2:$A$10000,">="&A70,Events!$A$2:$A$10000,"<"&EDATE(A70,1)) -> 0 | D70: =SUMIFS(Events!$D$2:$D$10000,Events!$A$2:$A$10000,">="&A70,Events!$A$2:$A$10000,"<"&EDATE(A70,1)) -> 0 | E70: =SUMIFS(Events!$E$2:$E$10000,Events!$A$2:$A$10000,">="&A70,Events!$A$2:$A$10000,"<"&EDATE(A70,1)) -> 0 | F70: =SUMIFS(Events!$F$2:$F$10000,Events!$A$2:$A$10000,">="&A70,Events!$A$2:$A$10000,"<"&EDATE(A70,1)) -> 0
A71: 42278 | B71: =COUNTIFS(Events!$A$2:$A$10000,">="&A71,Events!$A$2:$A$10000,"<"&EDATE(A71,1)) -> 0 | C71: =SUMIFS(Events!$C$2:$C$10000,Events!$A$2:$A$10000,">="&A71,Events!$A$2:$A$10000,"<"&EDATE(A71,1)) -> 0 | D71: =SUMIFS(Events!$D$2:$D$10000,Events!$A$2:$A$10000,">="&A71,Events!$A$2:$A$10000,"<"&EDATE(A71,1)) -> 0 | E71: =SUMIFS(Events!$E$2:$E$10000,Events!$A$2:$A$10000,">="&A71,Events!$A$2:$A$10000,"<"&EDATE(A71,1)) -> 0 | F71: =SUMIFS(Events!$F$2:$F$10000,Events!$A$2:$A$10000,">="&A71,Events!$A$2:$A$10000,"<"&EDATE(A71,1)) -> 0 | G71: TPP negotiations concluded among 12 economies, including the United States.
A72: 42309 | B72: =COUNTIFS(Events!$A$2:$A$10000,">="&A72,Events!$A$2:$A$10000,"<"&EDATE(A72,1)) -> 1 | C72: =SUMIFS(Events!$C$2:$C$10000,Events!$A$2:$A$10000,">="&A72,Events!$A$2:$A$10000,"<"&EDATE(A72,1)) -> 1 | D72: =SUMIFS(Events!$D$2:$D$10000,Events!$A$2:$A$10000,">="&A72,Events!$A$2:$A$10000,"<"&EDATE(A72,1)) -> 0 | E72: =SUMIFS(Events!$E$2:$E$10000,Events!$A$2:$A$10000,">="&A72,Events!$A$2:$A$10000,"<"&EDATE(A72,1)) -> 0 | F72: =SUMIFS(Events!$F$2:$F$10000,Events!$A$2:$A$10000,">="&A72,Events!$A$2:$A$10000,"<"&EDATE(A72,1)) -> 0
A73: 42339 | B73: =COUNTIFS(Events!$A$2:$A$10000,">="&A73,Events!$A$2:$A$10000,"<"&EDATE(A73,1)) -> 0 | C73: =SUMIFS(Events!$C$2:$C$10000,Events!$A$2:$A$10000,">="&A73,Events!$A$2:$A$10000,"<"&EDATE(A73,1)) -> 0 | D73: =SUMIFS(Events!$D$2:$D$10000,Events!$A$2:$A$10000,">="&A73,Events!$A$2:$A$10000,"<"&EDATE(A73,1)) -> 0 | E73: =SUMIFS(Events!$E$2:$E$10000,Events!$A$2:$A$10000,">="&A73,Events!$A$2:$A$10000,"<"&EDATE(A73,1)) -> 0 | F73: =SUMIFS(Events!$F$2:$F$10000,Events!$A$2:$A$10000,">="&A73,Events!$A$2:$A$10000,"<"&EDATE(A73,1)) -> 0
A74: 42370 | B74: =COUNTIFS(Events!$A$2:$A$10000,">="&A74,Events!$A$2:$A$10000,"<"&EDATE(A74,1)) -> 0 | C74: =SUMIFS(Events!$C$2:$C$10000,Events!$A$2:$A$10000,">="&A74,Events!$A$2:$A$10000,"<"&EDATE(A74,1)) -> 0 | D74: =SUMIFS(Events!$D$2:$D$10000,Events!$A$2:$A$10000,">="&A74,Events!$A$2:$A$10000,"<"&EDATE(A74,1)) -> 0 | E74: =SUMIFS(Events!$E$2:$E$10000,Events!$A$2:$A$10000,">="&A74,Events!$A$2:$A$10000,"<"&EDATE(A74,1)) -> 0 | F74: =SUMIFS(Events!$F$2:$F$10000,Events!$A$2:$A$10000,">="&A74,Events!$A$2:$A$10000,"<"&EDATE(A74,1)) -> 0
A75: 42401 | B75: =COUNTIFS(Events!$A$2:$A$10000,">="&A75,Events!$A$2:$A$10000,"<"&EDATE(A75,1)) -> 2 | C75: =SUMIFS(Events!$C$2:$C$10000,Events!$A$2:$A$10000,">="&A75,Events!$A$2:$A$10000,"<"&EDATE(A75,1)) -> 1 | D75: =SUMIFS(Events!$D$2:$D$10000,Events!$A$2:$A$10000,">="&A75,Events!$A$2:$A$10000,"<"&EDATE(A75,1)) -> 0 | E75: =SUMIFS(Events!$E$2:$E$10000,Events!$A$2:$A$10000,">="&A75,Events!$A$2:$A$10000,"<"&EDATE(A75,1)) -> 0 | F75: =SUMIFS(Events!$F$2:$F$10000,Events!$A$2:$A$10000,">="&A75,Events!$A$2:$A$10000,"<"&EDATE(A75,1)) -> 1 | G75: TPP agreement signed by 12 members.
A76: 42430 | B76: =COUNTIFS(Events!$A$2:$A$10000,">="&A76,Events!$A$2:$A$10000,"<"&EDATE(A76,1)) -> 0 | C76: =SUMIFS(Events!$C$2:$C$10000,Events!$A$2:$A$10000,">="&A76,Events!$A$2:$A$10000,"<"&EDATE(A76,1)) -> 0 | D76: =SUMIFS(Events!$D$2:$D$10000,Events!$A$2:$A$10000,">="&A76,Events!$A$2:$A$10000,"<"&EDATE(A76,1)) -> 0 | E76: =SUMIFS(Events!$E$2:$E$10000,Events!$A$2:$A$10000,">="&A76,Events!$A$2:$A$10000,"<"&EDATE(A76,1)) -> 0 | F76: =SUMIFS(Events!$F$2:$F$10000,Events!$A$2:$A$10000,">="&A76,Events!$A$2:$A$10000,"<"&EDATE(A76,1)) -> 0
A77: 42461 | B77: =COUNTIFS(Events!$A$2:$A$10000,">="&A77,Events!$A$2:$A$10000,"<"&EDATE(A77,1)) -> 2 | C77: =SUMIFS(Events!$C$2:$C$10000,Events!$A$2:$A$10000,">="&A77,Events!$A$2:$A$10000,"<"&EDATE(A77,1)) -> 1 | D77: =SUMIFS(Events!$D$2:$D$10000,Events!$A$2:$A$10000,">="&A77,Events!$A$2:$A$10000,"<"&EDATE(A77,1)) -> 0 | E77: =SUMIFS(Events!$E$2:$E$10000,Events!$A$2:$A$10000,">="&A77,Events!$A$2:$A$10000,"<"&EDATE(A77,1)) -> 0 | F77: =SUMIFS(Events!$F$2:$F$10000,Events!$A$2:$A$10000,">="&A77,Events!$A$2:$A$10000,"<"&EDATE(A77,1)) -> 1
A78: 42491 | B78: =COUNTIFS(Events!$A$2:$A$10000,">="&A78,Events!$A$2:$A$10000,"<"&EDATE(A78,1)) -> 1 | C78: =SUMIFS(Events!$C$2:$C$10000,Events!$A$2:$A$10000,">="&A78,Events!$A$2:$A$10000,"<"&EDATE(A78,1)) -> 1 | D78: =SUMIFS(Events!$D$2:$D$10000,Events!$A$2:$A$10000,">="&A78,Events!$A$2:$A$10000,"<"&EDATE(A78,1)) -> 0 | E78: =SUMIFS(Events!$E$2:$E$10000,Events!$A$2:$A$10000,">="&A78,Events!$A$2:$A$10000,"<"&EDATE(A78,1)) -> 0 | F78: =SUMIFS(Events!$F$2:$F$10000,Events!$A$2:$A$10000,">="&A78,Events!$A$2:$A$10000,"<"&EDATE(A78,1)) -> 0
A79: 42522 | B79: =COUNTIFS(Events!$A$2:$A$10000,">="&A79,Events!$A$2:$A$10000,"<"&EDATE(A79,1)) -> 0 | C79: =SUMIFS(Events!$C$2:$C$10000,Events!$A$2:$A$10000,">="&A79,Events!$A$2:$A$10000,"<"&EDATE(A79,1)) -> 0 | D79: =SUMIFS(Events!$D$2:$D$10000,Events!$A$2:$A$10000,">="&A79,Events!$A$2:$A$10000,"<"&EDATE(A79,1)) -> 0 | E79: =SUMIFS(Events!$E$2:$E$10000,Events!$A$2:$A$10000,">="&A79,Events!$A$2:$A$10000,"<"&EDATE(A79,1)) -> 0 | F79: =SUMIFS(Events!$F$2:$F$10000,Events!$A$2:$A$10000,">="&A79,Events!$A$2:$A$10000,"<"&EDATE(A79,1)) -> 0
A80: 42552 | B80: =COUNTIFS(Events!$A$2:$A$10000,">="&A80,Events!$A$2:$A$10000,"<"&EDATE(A80,1)) -> 1 | C80: =SUMIFS(Events!$C$2:$C$10000,Events!$A$2:$A$10000,">="&A80,Events!$A$2:$A$10000,"<"&EDATE(A80,1)) -> 1 | D80: =SUMIFS(Events!$D$2:$D$10000,Events!$A$2:$A$10000,">="&A80,Events!$A$2:$A$10000,"<"&EDATE(A80,1)) -> 0 | E80: =SUMIFS(Events!$E$2:$E$10000,Events!$A$2:$A$10000,">="&A80,Events!$A$2:$A$10000,"<"&EDATE(A80,1)) -> 0 | F80: =SUMIFS(Events!$F$2:$F$10000,Events!$A$2:$A$10000,">="&A80,Events!$A$2:$A$10000,"<"&EDATE(A80,1)) -> 0
A81: 42583 | B81: =COUNTIFS(Events!$A$2:$A$10000,">="&A81,Events!$A$2:$A$10000,"<"&EDATE(A81,1)) -> 0 | C81: =SUMIFS(Events!$C$2:$C$10000,Events!$A$2:$A$10000,">="&A81,Events!$A$2:$A$10000,"<"&EDATE(A81,1)) -> 0 | D81: =SUMIFS(Events!$D$2:$D$10000,Events!$A$2:$A$10000,">="&A81,Events!$A$2:$A$10000,"<"&EDATE(A81,1)) -> 0 | E81: =SUMIFS(Events!$E$2:$E$10000,Events!$A$2:$A$10000,">="&A81,Events!$A$2:$A$10000,"<"&EDATE(A81,1)) -> 0 | F81: =SUMIFS(Events!$F$2:$F$10000,Events!$A$2:$A$10000,">="&A81,Events!$A$2:$A$10000,"<"&EDATE(A81,1)) -> 0
A82: 42614 | B82: =COUNTIFS(Events!$A$2:$A$10000,">="&A82,Events!$A$2:$A$10000,"<"&EDATE(A82,1)) -> 1 | C82: =SUMIFS(Events!$C$2:$C$10000,Events!$A$2:$A$10000,">="&A82,Events!$A$2:$A$10000,"<"&EDATE(A82,1)) -> 1 | D82: =SUMIFS(Events!$D$2:$D$10000,Events!$A$2:$A$10000,">="&A82,Events!$A$2:$A$10000,"<"&EDATE(A82,1)) -> 0 | E82: =SUMIFS(Events!$E$2:$E$10000,Events!$A$2:$A$10000,">="&A82,Events!$A$2:$A$10000,"<"&EDATE(A82,1)) -> 0 | F82: =SUMIFS(Events!$F$2:$F$10000,Events!$A$2:$A$10000,">="&A82,Events!$A$2:$A$10000,"<"&EDATE(A82,1)) -> 0
A83: 42644 | B83: =COUNTIFS(Events!$A$2:$A$10000,">="&A83,Events!$A$2:$A$10000,"<"&EDATE(A83,1)) -> 0 | C83: =SUMIFS(Events!$C$2:$C$10000,Events!$A$2:$A$10000,">="&A83,Events!$A$2:$A$10000,"<"&EDATE(A83,1)) -> 0 | D83: =SUMIFS(Events!$D$2:$D$10000,Events!$A$2:$A$10000,">="&A83,Events!$A$2:$A$10000,"<"&EDATE(A83,1)) -> 0 | E83: =SUMIFS(Events!$E$2:$E$10000,Events!$A$2:$A$10000,">="&A83,Events!$A$2:$A$10000,"<"&EDATE(A83,1)) -> 0 | F83: =SUMIFS(Events!$F$2:$F$10000,Events!$A$2:$A$10000,">="&A83,Events!$A$2:$A$10000,"<"&EDATE(A83,1)) -> 0
A84: 42675 | B84: =COUNTIFS(Events!$A$2:$A$10000,">="&A84,Events!$A$2:$A$10000,"<"&EDATE(A84,1)) -> 0 | C84: =SUMIFS(Events!$C$2:$C$10000,Events!$A$2:$A$10000,">="&A84,Events!$A$2:$A$10000,"<"&EDATE(A84,1)) -> 0 | D84: =SUMIFS(Events!$D$2:$D$10000,Events!$A$2:$A$10000,">="&A84,Events!$A$2:$A$10000,"<"&EDATE(A84,1)) -> 0 | E84: =SUMIFS(Events!$E$2:$E$10000,Events!$A$2:$A$10000,">="&A84,Events!$A$2:$A$10000,"<"&EDATE(A84,1)) -> 0 | F84: =SUMIFS(Events!$F$2:$F$10000,Events!$A$2:$A$10000,">="&A84,Events!$A$2:$A$10000,"<"&EDATE(A84,1)) -> 0
A85: 42705 | B85: =COUNTIFS(Events!$A$2:$A$10000,">="&A85,Events!$A$2:$A$10000,"<"&EDATE(A85,1)) -> 0 | C85: =SUMIFS(Events!$C$2:$C$10000,Events!$A$2:$A$10000,">="&A85,Events!$A$2:$A$10000,"<"&EDATE(A85,1)) -> 0 | D85: =SUMIFS(Events!$D$2:$D$10000,Events!$A$2:$A$10000,">="&A85,Events!$A$2:$A$10000,"<"&EDATE(A85,1)) -> 0 | E85: =SUMIFS(Events!$E$2:$E$10000,Events!$A$2:$A$10000,">="&A85,Events!$A$2:$A$10000,"<"&EDATE(A85,1)) -> 0 | F85: =SUMIFS(Events!$F$2:$F$10000,Events!$A$2:$A$10000,">="&A85,Events!$A$2:$A$10000,"<"&EDATE(A85,1)) -> 0
A86: 42736 | B86: =COUNTIFS(Events!$A$2:$A$10000,">="&A86,Events!$A$2:$A$10000,"<"&EDATE(A86,1)) -> 1 | C86: =SUMIFS(Events!$C$2:$C$10000,Events!$A$2:$A$10000,">="&A86,Events!$A$2:$A$10000,"<"&EDATE(A86,1)) -> 0 | D86: =SUMIFS(Events!$D$2:$D$10000,Events!$A$2:$A$10000,">="&A86,Events!$A$2:$A$10000,"<"&EDATE(A86,1)) -> 0 | E86: =SUMIFS(Events!$E$2:$E$10000,Events!$A$2:$A$10000,">="&A86,Events!$A$2:$A$10000,"<"&EDATE(A86,1)) -> 0 | F86: =SUMIFS(Events!$F$2:$F$10000,Events!$A$2:$A$10000,">="&A86,Events!$A$2:$A$10000,"<"&EDATE(A86,1)) -> 1 | G86: Trump I begins; United States withdraws from TPP (23 Jan).
A87: 42767 | B87: =COUNTIFS(Events!$A$2:$A$10000,">="&A87,Events!$A$2:$A$10000,"<"&EDATE(A87,1)) -> 0 | C87: =SUMIFS(Events!$C$2:$C$10000,Events!$A$2:$A$10000,">="&A87,Events!$A$2:$A$10000,"<"&EDATE(A87,1)) -> 0 | D87: =SUMIFS(Events!$D$2:$D$10000,Events!$A$2:$A$10000,">="&A87,Events!$A$2:$A$10000,"<"&EDATE(A87,1)) -> 0 | E87: =SUMIFS(Events!$E$2:$E$10000,Events!$A$2:$A$10000,">="&A87,Events!$A$2:$A$10000,"<"&EDATE(A87,1)) -> 0 | F87: =SUMIFS(Events!$F$2:$F$10000,Events!$A$2:$A$10000,">="&A87,Events!$A$2:$A$10000,"<"&EDATE(A87,1)) -> 0
A88: 42795 | B88: =COUNTIFS(Events!$A$2:$A$10000,">="&A88,Events!$A$2:$A$10000,"<"&EDATE(A88,1)) -> 0 | C88: =SUMIFS(Events!$C$2:$C$10000,Events!$A$2:$A$10000,">="&A88,Events!$A$2:$A$10000,"<"&EDATE(A88,1)) -> 0 | D88: =SUMIFS(Events!$D$2:$D$10000,Events!$A$2:$A$10000,">="&A88,Events!$A$2:$A$10000,"<"&EDATE(A88,1)) -> 0 | E88: =SUMIFS(Events!$E$2:$E$10000,Events!$A$2:$A$10000,">="&A88,Events!$A$2:$A$10000,"<"&EDATE(A88,1)) -> 0 | F88: =SUMIFS(Events!$F$2:$F$10000,Events!$A$2:$A$10000,">="&A88,Events!$A$2:$A$10000,"<"&EDATE(A88,1)) -> 0
A89: 42826 | B89: =COUNTIFS(Events!$A$2:$A$10000,">="&A89,Events!$A$2:$A$10000,"<"&EDATE(A89,1)) -> 0 | C89: =SUMIFS(Events!$C$2:$C$10000,Events!$A$2:$A$10000,">="&A89,Events!$A$2:$A$10000,"<"&EDATE(A89,1)) -> 0 | D89: =SUMIFS(Events!$D$2:$D$10000,Events!$A$2:$A$10000,">="&A89,Events!$A$2:$A$10000,"<"&EDATE(A89,1)) -> 0 | E89: =SUMIFS(Events!$E$2:$E$10000,Events!$A$2:$A$10000,">="&A89,Events!$A$2:$A$10000,"<"&EDATE(A89,1)) -> 0 | F89: =SUMIFS(Events!$F$2:$F$10000,Events!$A$2:$A$10000,">="&A89,Events!$A$2:$A$10000,"<"&EDATE(A89,1)) -> 0
A90: 42856 | B90: =COUNTIFS(Events!$A$2:$A$10000,">="&A90,Events!$A$2:$A$10000,"<"&EDATE(A90,1)) -> 0 | C90: =SUMIFS(Events!$C$2:$C$10000,Events!$A$2:$A$10000,">="&A90,Events!$A$2:$A$10000,"<"&EDATE(A90,1)) -> 0 | D90: =SUMIFS(Events!$D$2:$D$10000,Events!$A$2:$A$10000,">="&A90,Events!$A$2:$A$10000,"<"&EDATE(A90,1)) -> 0 | E90: =SUMIFS(Events!$E$2:$E$10000,Events!$A$2:$A$10000,">="&A90,Events!$A$2:$A$10000,"<"&EDATE(A90,1)) -> 0 | F90: =SUMIFS(Events!$F$2:$F$10000,Events!$A$2:$A$10000,">="&A90,Events!$A$2:$A$10000,"<"&EDATE(A90,1)) -> 0
A91: 42887 | B91: =COUNTIFS(Events!$A$2:$A$10000,">="&A91,Events!$A$2:$A$10000,"<"&EDATE(A91,1)) -> 0 | C91: =SUMIFS(Events!$C$2:$C$10000,Events!$A$2:$A$10000,">="&A91,Events!$A$2:$A$10000,"<"&EDATE(A91,1)) -> 0 | D91: =SUMIFS(Events!$D$2:$D$10000,Events!$A$2:$A$10000,">="&A91,Events!$A$2:$A$10000,"<"&EDATE(A91,1)) -> 0 | E91: =SUMIFS(Events!$E$2:$E$10000,Events!$A$2:$A$10000,">="&A91,Events!$A$2:$A$10000,"<"&EDATE(A91,1)) -> 0 | F91: =SUMIFS(Events!$F$2:$F$10000,Events!$A$2:$A$10000,">="&A91,Events!$A$2:$A$10000,"<"&EDATE(A91,1)) -> 0
A92: 42917 | B92: =COUNTIFS(Events!$A$2:$A$10000,">="&A92,Events!$A$2:$A$10000,"<"&EDATE(A92,1)) -> 0 | C92: =SUMIFS(Events!$C$2:$C$10000,Events!$A$2:$A$10000,">="&A92,Events!$A$2:$A$10000,"<"&EDATE(A92,1)) -> 0 | D92: =SUMIFS(Events!$D$2:$D$10000,Events!$A$2:$A$10000,">="&A92,Events!$A$2:$A$10000,"<"&EDATE(A92,1)) -> 0 | E92: =SUMIFS(Events!$E$2:$E$10000,Events!$A$2:$A$10000,">="&A92,Events!$A$2:$A$10000,"<"&EDATE(A92,1)) -> 0 | F92: =SUMIFS(Events!$F$2:$F$10000,Events!$A$2:$A$10000,">="&A92,Events!$A$2:$A$10000,"<"&EDATE(A92,1)) -> 0
A93: 42948 | B93: =COUNTIFS(Events!$A$2:$A$10000,">="&A93,Events!$A$2:$A$10000,"<"&EDATE(A93,1)) -> 0 | C93: =SUMIFS(Events!$C$2:$C$10000,Events!$A$2:$A$10000,">="&A93,Events!$A$2:$A$10000,"<"&EDATE(A93,1)) -> 0 | D93: =SUMIFS(Events!$D$2:$D$10000,Events!$A$2:$A$10000,">="&A93,Events!$A$2:$A$10000,"<"&EDATE(A93,1)) -> 0 | E93: =SUMIFS(Events!$E$2:$E$10000,Events!$A$2:$A$10000,">="&A93,Events!$A$2:$A$10000,"<"&EDATE(A93,1)) -> 0 | F93: =SUMIFS(Events!$F$2:$F$10000,Events!$A$2:$A$10000,">="&A93,Events!$A$2:$A$10000,"<"&EDATE(A93,1)) -> 0
A94: 42979 | B94: =COUNTIFS(Events!$A$2:$A$10000,">="&A94,Events!$A$2:$A$10000,"<"&EDATE(A94,1)) -> 0 | C94: =SUMIFS(Events!$C$2:$C$10000,Events!$A$2:$A$10000,">="&A94,Events!$A$2:$A$10000,"<"&EDATE(A94,1)) -> 0 | D94: =SUMIFS(Events!$D$2:$D$10000,Events!$A$2:$A$10000,">="&A94,Events!$A$2:$A$10000,"<"&EDATE(A94,1)) -> 0 | E94: =SUMIFS(Events!$E$2:$E$10000,Events!$A$2:$A$10000,">="&A94,Events!$A$2:$A$10000,"<"&EDATE(A94,1)) -> 0 | F94: =SUMIFS(Events!$F$2:$F$10000,Events!$A$2:$A$10000,">="&A94,Events!$A$2:$A$10000,"<"&EDATE(A94,1)) -> 0
A95: 43009 | B95: =COUNTIFS(Events!$A$2:$A$10000,">="&A95,Events!$A$2:$A$10000,"<"&EDATE(A95,1)) -> 0 | C95: =SUMIFS(Events!$C$2:$C$10000,Events!$A$2:$A$10000,">="&A95,Events!$A$2:$A$10000,"<"&EDATE(A95,1)) -> 0 | D95: =SUMIFS(Events!$D$2:$D$10000,Events!$A$2:$A$10000,">="&A95,Events!$A$2:$A$10000,"<"&EDATE(A95,1)) -> 0 | E95: =SUMIFS(Events!$E$2:$E$10000,Events!$A$2:$A$10000,">="&A95,Events!$A$2:$A$10000,"<"&EDATE(A95,1)) -> 0 | F95: =SUMIFS(Events!$F$2:$F$10000,Events!$A$2:$A$10000,">="&A95,Events!$A$2:$A$10000,"<"&EDATE(A95,1)) -> 0
A96: 43040 | B96: =COUNTIFS(Events!$A$2:$A$10000,">="&A96,Events!$A$2:$A$10000,"<"&EDATE(A96,1)) -> 0 | C96: =SUMIFS(Events!$C$2:$C$10000,Events!$A$2:$A$10000,">="&A96,Events!$A$2:$A$10000,"<"&EDATE(A96,1)) -> 0 | D96: =SUMIFS(Events!$D$2:$D$10000,Events!$A$2:$A$10000,">="&A96,Events!$A$2:$A$10000,"<"&EDATE(A96,1)) -> 0 | E96: =SUMIFS(Events!$E$2:$E$10000,Events!$A$2:$A$10000,">="&A96,Events!$A$2:$A$10000,"<"&EDATE(A96,1)) -> 0 | F96: =SUMIFS(Events!$F$2:$F$10000,Events!$A$2:$A$10000,">="&A96,Events!$A$2:$A$10000,"<"&EDATE(A96,1)) -> 0
A97: 43070 | B97: =COUNTIFS(Events!$A$2:$A$10000,">="&A97,Events!$A$2:$A$10000,"<"&EDATE(A97,1)) -> 0 | C97: =SUMIFS(Events!$C$2:$C$10000,Events!$A$2:$A$10000,">="&A97,Events!$A$2:$A$10000,"<"&EDATE(A97,1)) -> 0 | D97: =SUMIFS(Events!$D$2:$D$10000,Events!$A$2:$A$10000,">="&A97,Events!$A$2:$A$10000,"<"&EDATE(A97,1)) -> 0 | E97: =SUMIFS(Events!$E$2:$E$10000,Events!$A$2:$A$10000,">="&A97,Events!$A$2:$A$10000,"<"&EDATE(A97,1)) -> 0 | F97: =SUMIFS(Events!$F$2:$F$10000,Events!$A$2:$A$10000,">="&A97,Events!$A$2:$A$10000,"<"&EDATE(A97,1)) -> 0
A98: 43101 | B98: =COUNTIFS(Events!$A$2:$A$10000,">="&A98,Events!$A$2:$A$10000,"<"&EDATE(A98,1)) -> 2 | C98: =SUMIFS(Events!$C$2:$C$10000,Events!$A$2:$A$10000,">="&A98,Events!$A$2:$A$10000,"<"&EDATE(A98,1)) -> 0 | D98: =SUMIFS(Events!$D$2:$D$10000,Events!$A$2:$A$10000,">="&A98,Events!$A$2:$A$10000,"<"&EDATE(A98,1)) -> 0 | E98: =SUMIFS(Events!$E$2:$E$10000,Events!$A$2:$A$10000,">="&A98,Events!$A$2:$A$10000,"<"&EDATE(A98,1)) -> 1 | F98: =SUMIFS(Events!$F$2:$F$10000,Events!$A$2:$A$10000,">="&A98,Events!$A$2:$A$10000,"<"&EDATE(A98,1)) -> 1
A99: 43132 | B99: =COUNTIFS(Events!$A$2:$A$10000,">="&A99,Events!$A$2:$A$10000,"<"&EDATE(A99,1)) -> 0 | C99: =SUMIFS(Events!$C$2:$C$10000,Events!$A$2:$A$10000,">="&A99,Events!$A$2:$A$10000,"<"&EDATE(A99,1)) -> 0 | D99: =SUMIFS(Events!$D$2:$D$10000,Events!$A$2:$A$10000,">="&A99,Events!$A$2:$A$10000,"<"&EDATE(A99,1)) -> 0 | E99: =SUMIFS(Events!$E$2:$E$10000,Events!$A$2:$A$10000,">="&A99,Events!$A$2:$A$10000,"<"&EDATE(A99,1)) -> 0 | F99: =SUMIFS(Events!$F$2:$F$10000,Events!$A$2:$A$10000,">="&A99,Events!$A$2:$A$10000,"<"&EDATE(A99,1)) -> 0
A100: 43160 | B100: =COUNTIFS(Events!$A$2:$A$10000,">="&A100,Events!$A$2:$A$10000,"<"&EDATE(A100,1)) -> 3 | C100: =SUMIFS(Events!$C$2:$C$10000,Events!$A$2:$A$10000,">="&A100,Events!$A$2:$A$10000,"<"&EDATE(A100,1)) -> 3 | D100: =SUMIFS(Events!$D$2:$D$10000,Events!$A$2:$A$10000,">="&A100,Events!$A$2:$A$10000,"<"&EDATE(A100,1)) -> 0 | E100: =SUMIFS(Events!$E$2:$E$10000,Events!$A$2:$A$10000,">="&A100,Events!$A$2:$A$10000,"<"&EDATE(A100,1)) -> 0 | F100: =SUMIFS(Events!$F$2:$F$10000,Events!$A$2:$A$10000,">="&A100,Events!$A$2:$A$10000,"<"&EDATE(A100,1)) -> 0 | G100: CPTPP signed by 11 countries without the United States (8 Mar); US Section 232 steel/aluminium tariffs take effect.
A101: 43191 | B101: =COUNTIFS(Events!$A$2:$A$10000,">="&A101,Events!$A$2:$A$10000,"<"&EDATE(A101,1)) -> 0 | C101: =SUMIFS(Events!$C$2:$C$10000,Events!$A$2:$A$10000,">="&A101,Events!$A$2:$A$10000,"<"&EDATE(A101,1)) -> 0 | D101: =SUMIFS(Events!$D$2:$D$10000,Events!$A$2:$A$10000,">="&A101,Events!$A$2:$A$10000,"<"&EDATE(A101,1)) -> 0 | E101: =SUMIFS(Events!$E$2:$E$10000,Events!$A$2:$A$10000,">="&A101,Events!$A$2:$A$10000,"<"&EDATE(A101,1)) -> 0 | F101: =SUMIFS(Events!$F$2:$F$10000,Events!$A$2:$A$10000,">="&A101,Events!$A$2:$A$10000,"<"&EDATE(A101,1)) -> 0
A102: 43221 | B102: =COUNTIFS(Events!$A$2:$A$10000,">="&A102,Events!$A$2:$A$10000,"<"&EDATE(A102,1)) -> 0 | C102: =SUMIFS(Events!$C$2:$C$10000,Events!$A$2:$A$10000,">="&A102,Events!$A$2:$A$10000,"<"&EDATE(A102,1)) -> 0 | D102: =SUMIFS(Events!$D$2:$D$10000,Events!$A$2:$A$10000,">="&A102,Events!$A$2:$A$10000,"<"&EDATE(A102,1)) -> 0 | E102: =SUMIFS(Events!$E$2:$E$10000,Events!$A$2:$A$10000,">="&A102,Events!$A$2:$A$10000,"<"&EDATE(A102,1)) -> 0 | F102: =SUMIFS(Events!$F$2:$F$10000,Events!$A$2:$A$10000,">="&A102,Events!$A$2:$A$10000,"<"&EDATE(A102,1)) -> 0
A103: 43252 | B103: =COUNTIFS(Events!$A$2:$A$10000,">="&A103,Events!$A$2:$A$10000,"<"&EDATE(A103,1)) -> 0 | C103: =SUMIFS(Events!$C$2:$C$10000,Events!$A$2:$A$10000,">="&A103,Events!$A$2:$A$10000,"<"&EDATE(A103,1)) -> 0 | D103: =SUMIFS(Events!$D$2:$D$10000,Events!$A$2:$A$10000,">="&A103,Events!$A$2:$A$10000,"<"&EDATE(A103,1)) -> 0 | E103: =SUMIFS(Events!$E$2:$E$10000,Events!$A$2:$A$10000,">="&A103,Events!$A$2:$A$10000,"<"&EDATE(A103,1)) -> 0 | F103: =SUMIFS(Events!$F$2:$F$10000,Events!$A$2:$A$10000,">="&A103,Events!$A$2:$A$10000,"<"&EDATE(A103,1)) -> 0
A104: 43282 | B104: =COUNTIFS(Events!$A$2:$A$10000,">="&A104,Events!$A$2:$A$10000,"<"&EDATE(A104,1)) -> 1 | C104: =SUMIFS(Events!$C$2:$C$10000,Events!$A$2:$A$10000,">="&A104,Events!$A$2:$A$10000,"<"&EDATE(A104,1)) -> 0 | D104: =SUMIFS(Events!$D$2:$D$10000,Events!$A$2:$A$10000,">="&A104,Events!$A$2:$A$10000,"<"&EDATE(A104,1)) -> 0 | E104: =SUMIFS(Events!$E$2:$E$10000,Events!$A$2:$A$10000,">="&A104,Events!$A$2:$A$10000,"<"&EDATE(A104,1)) -> 1 | F104: =SUMIFS(Events!$F$2:$F$10000,Events!$A$2:$A$10000,">="&A104,Events!$A$2:$A$10000,"<"&EDATE(A104,1)) -> 0 | G104: US–China tariff escalation begins with Section 301 tariffs on major Chinese imports.
A105: 43313 | B105: =COUNTIFS(Events!$A$2:$A$10000,">="&A105,Events!$A$2:$A$10000,"<"&EDATE(A105,1)) -> 0 | C105: =SUMIFS(Events!$C$2:$C$10000,Events!$A$2:$A$10000,">="&A105,Events!$A$2:$A$10000,"<"&EDATE(A105,1)) -> 0 | D105: =SUMIFS(Events!$D$2:$D$10000,Events!$A$2:$A$10000,">="&A105,Events!$A$2:$A$10000,"<"&EDATE(A105,1)) -> 0 | E105: =SUMIFS(Events!$E$2:$E$10000,Events!$A$2:$A$10000,">="&A105,Events!$A$2:$A$10000,"<"&EDATE(A105,1)) -> 0 | F105: =SUMIFS(Events!$F$2:$F$10000,Events!$A$2:$A$10000,">="&A105,Events!$A$2:$A$10000,"<"&EDATE(A105,1)) -> 0
A106: 43344 | B106: =COUNTIFS(Events!$A$2:$A$10000,">="&A106,Events!$A$2:$A$10000,"<"&EDATE(A106,1)) -> 0 | C106: =SUMIFS(Events!$C$2:$C$10000,Events!$A$2:$A$10000,">="&A106,Events!$A$2:$A$10000,"<"&EDATE(A106,1)) -> 0 | D106: =SUMIFS(Events!$D$2:$D$10000,Events!$A$2:$A$10000,">="&A106,Events!$A$2:$A$10000,"<"&EDATE(A106,1)) -> 0 | E106: =SUMIFS(Events!$E$2:$E$10000,Events!$A$2:$A$10000,">="&A106,Events!$A$2:$A$10000,"<"&EDATE(A106,1)) -> 0 | F106: =SUMIFS(Events!$F$2:$F$10000,Events!$A$2:$A$10000,">="&A106,Events!$A$2:$A$10000,"<"&EDATE(A106,1)) -> 0
A107: 43374 | B107: =COUNTIFS(Events!$A$2:$A$10000,">="&A107,Events!$A$2:$A$10000,"<"&EDATE(A107,1)) -> 0 | C107: =SUMIFS(Events!$C$2:$C$10000,Events!$A$2:$A$10000,">="&A107,Events!$A$2:$A$10000,"<"&EDATE(A107,1)) -> 0 | D107: =SUMIFS(Events!$D$2:$D$10000,Events!$A$2:$A$10000,">="&A107,Events!$A$2:$A$10000,"<"&EDATE(A107,1)) -> 0 | E107: =SUMIFS(Events!$E$2:$E$10000,Events!$A$2:$A$10000,">="&A107,Events!$A$2:$A$10000,"<"&EDATE(A107,1)) -> 0 | F107: =SUMIFS(Events!$F$2:$F$10000,Events!$A$2:$A$10000,">="&A107,Events!$A$2:$A$10000,"<"&EDATE(A107,1)) -> 0
A108: 43405 | B108: =COUNTIFS(Events!$A$2:$A$10000,">="&A108,Events!$A$2:$A$10000,"<"&EDATE(A108,1)) -> 0 | C108: =SUMIFS(Events!$C$2:$C$10000,Events!$A$2:$A$10000,">="&A108,Events!$A$2:$A$10000,"<"&EDATE(A108,1)) -> 0 | D108: =SUMIFS(Events!$D$2:$D$10000,Events!$A$2:$A$10000,">="&A108,Events!$A$2:$A$10000,"<"&EDATE(A108,1)) -> 0 | E108: =SUMIFS(Events!$E$2:$E$10000,Events!$A$2:$A$10000,">="&A108,Events!$A$2:$A$10000,"<"&EDATE(A108,1)) -> 0 | F108: =SUMIFS(Events!$F$2:$F$10000,Events!$A$2:$A$10000,">="&A108,Events!$A$2:$A$10000,"<"&EDATE(A108,1)) -> 0
A109: 43435 | B109: =COUNTIFS(Events!$A$2:$A$10000,">="&A109,Events!$A$2:$A$10000,"<"&EDATE(A109,1)) -> 0 | C109: =SUMIFS(Events!$C$2:$C$10000,Events!$A$2:$A$10000,">="&A109,Events!$A$2:$A$10000,"<"&EDATE(A109,1)) -> 0 | D109: =SUMIFS(Events!$D$2:$D$10000,Events!$A$2:$A$10000,">="&A109,Events!$A$2:$A$10000,"<"&EDATE(A109,1)) -> 0 | E109: =SUMIFS(Events!$E$2:$E$10000,Events!$A$2:$A$10000,">="&A109,Events!$A$2:$A$10000,"<"&EDATE(A109,1)) -> 0 | F109: =SUMIFS(Events!$F$2:$F$10000,Events!$A$2:$A$10000,">="&A109,Events!$A$2:$A$10000,"<"&EDATE(A109,1)) -> 0
A110: 43466 | B110: =COUNTIFS(Events!$A$2:$A$10000,">="&A110,Events!$A$2:$A$10000,"<"&EDATE(A110,1)) -> 0 | C110: =SUMIFS(Events!$C$2:$C$10000,Events!$A$2:$A$10000,">="&A110,Events!$A$2:$A$10000,"<"&EDATE(A110,1)) -> 0 | D110: =SUMIFS(Events!$D$2:$D$10000,Events!$A$2:$A$10000,">="&A110,Events!$A$2:$A$10000,"<"&EDATE(A110,1)) -> 0 | E110: =SUMIFS(Events!$E$2:$E$10000,Events!$A$2:$A$10000,">="&A110,Events!$A$2:$A$10000,"<"&EDATE(A110,1)) -> 0 | F110: =SUMIFS(Events!$F$2:$F$10000,Events!$A$2:$A$10000,">="&A110,Events!$A$2:$A$10000,"<"&EDATE(A110,1)) -> 0
A111: 43497 | B111: =COUNTIFS(Events!$A$2:$A$10000,">="&A111,Events!$A$2:$A$10000,"<"&EDATE(A111,1)) -> 0 | C111: =SUMIFS(Events!$C$2:$C$10000,Events!$A$2:$A$10000,">="&A111,Events!$A$2:$A$10000,"<"&EDATE(A111,1)) -> 0 | D111: =SUMIFS(Events!$D$2:$D$10000,Events!$A$2:$A$10000,">="&A111,Events!$A$2:$A$10000,"<"&EDATE(A111,1)) -> 0 | E111: =SUMIFS(Events!$E$2:$E$10000,Events!$A$2:$A$10000,">="&A111,Events!$A$2:$A$10000,"<"&EDATE(A111,1)) -> 0 | F111: =SUMIFS(Events!$F$2:$F$10000,Events!$A$2:$A$10000,">="&A111,Events!$A$2:$A$10000,"<"&EDATE(A111,1)) -> 0
A112: 43525 | B112: =COUNTIFS(Events!$A$2:$A$10000,">="&A112,Events!$A$2:$A$10000,"<"&EDATE(A112,1)) -> 0 | C112: =SUMIFS(Events!$C$2:$C$10000,Events!$A$2:$A$10000,">="&A112,Events!$A$2:$A$10000,"<"&EDATE(A112,1)) -> 0 | D112: =SUMIFS(Events!$D$2:$D$10000,Events!$A$2:$A$10000,">="&A112,Events!$A$2:$A$10000,"<"&EDATE(A112,1)) -> 0 | E112: =SUMIFS(Events!$E$2:$E$10000,Events!$A$2:$A$10000,">="&A112,Events!$A$2:$A$10000,"<"&EDATE(A112,1)) -> 0 | F112: =SUMIFS(Events!$F$2:$F$10000,Events!$A$2:$A$10000,">="&A112,Events!$A$2:$A$10000,"<"&EDATE(A112,1)) -> 0
A113: 43556 | B113: =COUNTIFS(Events!$A$2:$A$10000,">="&A113,Events!$A$2:$A$10000,"<"&EDATE(A113,1)) -> 0 | C113: =SUMIFS(Events!$C$2:$C$10000,Events!$A$2:$A$10000,">="&A113,Events!$A$2:$A$10000,"<"&EDATE(A113,1)) -> 0 | D113: =SUMIFS(Events!$D$2:$D$10000,Events!$A$2:$A$10000,">="&A113,Events!$A$2:$A$10000,"<"&EDATE(A113,1)) -> 0 | E113: =SUMIFS(Events!$E$2:$E$10000,Events!$A$2:$A$10000,">="&A113,Events!$A$2:$A$10000,"<"&EDATE(A113,1)) -> 0 | F113: =SUMIFS(Events!$F$2:$F$10000,Events!$A$2:$A$10000,">="&A113,Events!$A$2:$A$10000,"<"&EDATE(A113,1)) -> 0
A114: 43586 | B114: =COUNTIFS(Events!$A$2:$A$10000,">="&A114,Events!$A$2:$A$10000,"<"&EDATE(A114,1)) -> 0 | C114: =SUMIFS(Events!$C$2:$C$10000,Events!$A$2:$A$10000,">="&A114,Events!$A$2:$A$10000,"<"&EDATE(A114,1)) -> 0 | D114: =SUMIFS(Events!$D$2:$D$10000,Events!$A$2:$A$10000,">="&A114,Events!$A$2:$A$10000,"<"&EDATE(A114,1)) -> 0 | E114: =SUMIFS(Events!$E$2:$E$10000,Events!$A$2:$A$10000,">="&A114,Events!$A$2:$A$10000,"<"&EDATE(A114,1)) -> 0 | F114: =SUMIFS(Events!$F$2:$F$10000,Events!$A$2:$A$10000,">="&A114,Events!$A$2:$A$10000,"<"&EDATE(A114,1)) -> 0
A115: 43617 | B115: =COUNTIFS(Events!$A$2:$A$10000,">="&A115,Events!$A$2:$A$10000,"<"&EDATE(A115,1)) -> 1 | C115: =SUMIFS(Events!$C$2:$C$10000,Events!$A$2:$A$10000,">="&A115,Events!$A$2:$A$10000,"<"&EDATE(A115,1)) -> 0 | D115: =SUMIFS(Events!$D$2:$D$10000,Events!$A$2:$A$10000,">="&A115,Events!$A$2:$A$10000,"<"&EDATE(A115,1)) -> 0 | E115: =SUMIFS(Events!$E$2:$E$10000,Events!$A$2:$A$10000,">="&A115,Events!$A$2:$A$10000,"<"&EDATE(A115,1)) -> 0 | F115: =SUMIFS(Events!$F$2:$F$10000,Events!$A$2:$A$10000,">="&A115,Events!$A$2:$A$10000,"<"&EDATE(A115,1)) -> 1
A116: 43647 | B116: =COUNTIFS(Events!$A$2:$A$10000,">="&A116,Events!$A$2:$A$10000,"<"&EDATE(A116,1)) -> 0 | C116: =SUMIFS(Events!$C$2:$C$10000,Events!$A$2:$A$10000,">="&A116,Events!$A$2:$A$10000,"<"&EDATE(A116,1)) -> 0 | D116: =SUMIFS(Events!$D$2:$D$10000,Events!$A$2:$A$10000,">="&A116,Events!$A$2:$A$10000,"<"&EDATE(A116,1)) -> 0 | E116: =SUMIFS(Events!$E$2:$E$10000,Events!$A$2:$A$10000,">="&A116,Events!$A$2:$A$10000,"<"&EDATE(A116,1)) -> 0 | F116: =SUMIFS(Events!$F$2:$F$10000,Events!$A$2:$A$10000,">="&A116,Events!$A$2:$A$10000,"<"&EDATE(A116,1)) -> 0
... A131: 44105 | B131: =COUNTIFS(Events!$A$2:$A$10000,">="&A131,Events!$A$2:$A$10000,"<"&EDATE(A131,1)) -> 3 | C131: =SUMIFS(Events!$C$2:$C$10000,Events!$A$2:$A$10000,">="&A131,Events!$A$2:$A$10000,"<"&EDATE(A131,1)) -> 3 | D131: =SUMIFS(Events!$D$2:$D$10000,Events!$A$2:$A$10000,">="&A131,Events!$A$2:$A$10000,"<"&EDATE(A131,1)) -> 0 | E131: =SUMIFS(Events!$E$2:$E$10000,Events!$A$2:$A$10000,">="&A131,Events!$A$2:$A$10000,"<"&EDATE(A131,1)) -> 0 | F131: =SUMIFS(Events!$F$2:$F$10000,Events!$A$2:$A$10000,">="&A131,Events!$A$2:$A$10000,"<"&EDATE(A131,1)) -> 0
A132: 44136 | B132: =COUNTIFS(Events!$A$2:$A$10000,">="&A132,Events!$A$2:$A$10000,"<"&EDATE(A132,1)) -> 1 | C132: =SUMIFS(Events!$C$2:$C$10000,Events!$A$2:$A$10000,">="&A132,Events!$A$2:$A$10000,"<"&EDATE(A132,1)) -> 0 | D132: =SUMIFS(Events!$D$2:$D$10000,Events!$A$2:$A$10000,">="&A132,Events!$A$2:$A$10000,"<"&EDATE(A132,1)) -> 0 | E132: =SUMIFS(Events!$E$2:$E$10000,Events!$A$2:$A$10000,">="&A132,Events!$A$2:$A$10000,"<"&EDATE(A132,1)) -> 1 | F132: =SUMIFS(Events!$F$2:$F$10000,Events!$A$2:$A$10000,">="&A132,Events!$A$2:$A$10000,"<"&EDATE(A132,1)) -> 0 | G132: RCEP signed by 15 Asia-Pacific economies (15 Nov).
A133: 44166 | B133: =COUNTIFS(Events!$A$2:$A$10000,">="&A133,Events!$A$2:$A$10000,"<"&EDATE(A133,1)) -> 0 | C133: =SUMIFS(Events!$C$2:$C$10000,Events!$A$2:$A$10000,">="&A133,Events!$A$2:$A$10000,"<"&EDATE(A133,1)) -> 0 | D133: =SUMIFS(Events!$D$2:$D$10000,Events!$A$2:$A$10000,">="&A133,Events!$A$2:$A$10000,"<"&EDATE(A133,1)) -> 0 | E133: =SUMIFS(Events!$E$2:$E$10000,Events!$A$2:$A$10000,">="&A133,Events!$A$2:$A$10000,"<"&EDATE(A133,1)) -> 0 | F133: =SUMIFS(Events!$F$2:$F$10000,Events!$A$2:$A$10000,">="&A133,Events!$A$2:$A$10000,"<"&EDATE(A133,1)) -> 0
A134: 44197 | B134: =COUNTIFS(Events!$A$2:$A$10000,">="&A134,Events!$A$2:$A$10000,"<"&EDATE(A134,1)) -> 0 | C134: =SUMIFS(Events!$C$2:$C$10000,Events!$A$2:$A$10000,">="&A134,Events!$A$2:$A$10000,"<"&EDATE(A134,1)) -> 0 | D134: =SUMIFS(Events!$D$2:$D$10000,Events!$A$2:$A$10000,">="&A134,Events!$A$2:$A$10000,"<"&EDATE(A134,1)) -> 0 | E134: =SUMIFS(Events!$E$2:$E$10000,Events!$A$2:$A$10000,">="&A134,Events!$A$2:$A$10000,"<"&EDATE(A134,1)) -> 0 | F134: =SUMIFS(Events!$F$2:$F$10000,Events!$A$2:$A$10000,">="&A134,Events!$A$2:$A$10000,"<"&EDATE(A134,1)) -> 0 | G134: Biden presidency begins.
A135: 44228 | B135: =COUNTIFS(Events!$A$2:$A$10000,">="&A135,Events!$A$2:$A$10000,"<"&EDATE(A135,1)) -> 0 | C135: =SUMIFS(Events!$C$2:$C$10000,Events!$A$2:$A$10000,">="&A135,Events!$A$2:$A$10000,"<"&EDATE(A135,1)) -> 0 | D135: =SUMIFS(Events!$D$2:$D$10000,Events!$A$2:$A$10000,">="&A135,Events!$A$2:$A$10000,"<"&EDATE(A135,1)) -> 0 | E135: =SUMIFS(Events!$E$2:$E$10000,Events!$A$2:$A$10000,">="&A135,Events!$A$2:$A$10000,"<"&EDATE(A135,1)) -> 0 | F135: =SUMIFS(Events!$F$2:$F$10000,Events!$A$2:$A$10000,">="&A135,Events!$A$2:$A$10000,"<"&EDATE(A135,1)) -> 0
A136: 44256 | B136: =COUNTIFS(Events!$A$2:$A$10000,">="&A136,Events!$A$2:$A$10000,"<"&EDATE(A136,1)) -> 0 | C136: =SUMIFS(Events!$C$2:$C$10000,Events!$A$2:$A$10000,">="&A136,Events!$A$2:$A$10000,"<"&EDATE(A136,1)) -> 0 | D136: =SUMIFS(Events!$D$2:$D$10000,Events!$A$2:$A$10000,">="&A136,Events!$A$2:$A$10000,"<"&EDATE(A136,1)) -> 0 | E136: =SUMIFS(Events!$E$2:$E$10000,Events!$A$2:$A$10000,">="&A136,Events!$A$2:$A$10000,"<"&EDATE(A136,1)) -> 0 | F136: =SUMIFS(Events!$F$2:$F$10000,Events!$A$2:$A$10000,">="&A136,Events!$A$2:$A$10000,"<"&EDATE(A136,1)) -> 0
A137: 44287 | B137: =COUNTIFS(Events!$A$2:$A$10000,">="&A137,Events!$A$2:$A$10000,"<"&EDATE(A137,1)) -> 0 | C137: =SUMIFS(Events!$C$2:$C$10000,Events!$A$2:$A$10000,">="&A137,Events!$A$2:$A$10000,"<"&EDATE(A137,1)) -> 0 | D137: =SUMIFS(Events!$D$2:$D$10000,Events!$A$2:$A$10000,">="&A137,Events!$A$2:$A$10000,"<"&EDATE(A137,1)) -> 0 | E137: =SUMIFS(Events!$E$2:$E$10000,Events!$A$2:$A$10000,">="&A137,Events!$A$2:$A$10000,"<"&EDATE(A137,1)) -> 0 | F137: =SUMIFS(Events!$F$2:$F$10000,Events!$A$2:$A$10000,">="&A137,Events!$A$2:$A$10000,"<"&EDATE(A137,1)) -> 0
A138: 44317 | B138: =COUNTIFS(Events!$A$2:$A$10000,">="&A138,Events!$A$2:$A$10000,"<"&EDATE(A138,1)) -> 0 | C138: =SUMIFS(Events!$C$2:$C$10000,Events!$A$2:$A$10000,">="&A138,Events!$A$2:$A$10000,"<"&EDATE(A138,1)) -> 0 | D138: =SUMIFS(Events!$D$2:$D$10000,Events!$A$2:$A$10000,">="&A138,Events!$A$2:$A$10000,"<"&EDATE(A138,1)) -> 0 | E138: =SUMIFS(Events!$E$2:$E$10000,Events!$A$2:$A$10000,">="&A138,Events!$A$2:$A$10000,"<"&EDATE(A138,1)) -> 0 | F138: =SUMIFS(Events!$F$2:$F$10000,Events!$A$2:$A$10000,">="&A138,Events!$A$2:$A$10000,"<"&EDATE(A138,1)) -> 0
A139: 44348 | B139: =COUNTIFS(Events!$A$2:$A$10000,">="&A139,Events!$A$2:$A$10000,"<"&EDATE(A139,1)) -> 0 | C139: =SUMIFS(Events!$C$2:$C$10000,Events!$A$2:$A$10000,">="&A139,Events!$A$2:$A$10000,"<"&EDATE(A139,1)) -> 0 | D139: =SUMIFS(Events!$D$2:$D$10000,Events!$A$2:$A$10000,">="&A139,Events!$A$2:$A$10000,"<"&EDATE(A139,1)) -> 0 | E139: =SUMIFS(Events!$E$2:$E$10000,Events!$A$2:$A$10000,">="&A139,Events!$A$2:$A$10000,"<"&EDATE(A139,1)) -> 0 | F139: =SUMIFS(Events!$F$2:$F$10000,Events!$A$2:$A$10000,">="&A139,Events!$A$2:$A$10000,"<"&EDATE(A139,1)) -> 0
A140: 44378 | B140: =COUNTIFS(Events!$A$2:$A$10000,">="&A140,Events!$A$2:$A$10000,"<"&EDATE(A140,1)) -> 2 | C140: =SUMIFS(Events!$C$2:$C$10000,Events!$A$2:$A$10000,">="&A140,Events!$A$2:$A$10000,"<"&EDATE(A140,1)) -> 2 | D140: =SUMIFS(Events!$D$2:$D$10000,Events!$A$2:$A$10000,">="&A140,Events!$A$2:$A$10000,"<"&EDATE(A140,1)) -> 0 | E140: =SUMIFS(Events!$E$2:$E$10000,Events!$A$2:$A$10000,">="&A140,Events!$A$2:$A$10000,"<"&EDATE(A140,1)) -> 0 | F140: =SUMIFS(Events!$F$2:$F$10000,Events!$A$2:$A$10000,">="&A140,Events!$A$2:$A$10000,"<"&EDATE(A140,1)) -> 0
A141: 44409 | B141: =COUNTIFS(Events!$A$2:$A$10000,">="&A141,Events!$A$2:$A$10000,"<"&EDATE(A141,1)) -> 0 | C141: =SUMIFS(Events!$C$2:$C$10000,Events!$A$2:$A$10000,">="&A141,Events!$A$2:$A$10000,"<"&EDATE(A141,1)) -> 0 | D141: =SUMIFS(Events!$D$2:$D$10000,Events!$A$2:$A$10000,">="&A141,Events!$A$2:$A$10000,"<"&EDATE(A141,1)) -> 0 | E141: =SUMIFS(Events!$E$2:$E$10000,Events!$A$2:$A$10000,">="&A141,Events!$A$2:$A$10000,"<"&EDATE(A141,1)) -> 0 | F141: =SUMIFS(Events!$F$2:$F$10000,Events!$A$2:$A$10000,">="&A141,Events!$A$2:$A$10000,"<"&EDATE(A141,1)) -> 0
A142: 44440 | B142: =COUNTIFS(Events!$A$2:$A$10000,">="&A142,Events!$A$2:$A$10000,"<"&EDATE(A142,1)) -> 0 | C142: =SUMIFS(Events!$C$2:$C$10000,Events!$A$2:$A$10000,">="&A142,Events!$A$2:$A$10000,"<"&EDATE(A142,1)) -> 0 | D142: =SUMIFS(Events!$D$2:$D$10000,Events!$A$2:$A$10000,">="&A142,Events!$A$2:$A$10000,"<"&EDATE(A142,1)) -> 0 | E142: =SUMIFS(Events!$E$2:$E$10000,Events!$A$2:$A$10000,">="&A142,Events!$A$2:$A$10000,"<"&EDATE(A142,1)) -> 0 | F142: =SUMIFS(Events!$F$2:$F$10000,Events!$A$2:$A$10000,">="&A142,Events!$A$2:$A$10000,"<"&EDATE(A142,1)) -> 0
A143: 44470 | B143: =COUNTIFS(Events!$A$2:$A$10000,">="&A143,Events!$A$2:$A$10000,"<"&EDATE(A143,1)) -> 1 | C143: =SUMIFS(Events!$C$2:$C$10000,Events!$A$2:$A$10000,">="&A143,Events!$A$2:$A$10000,"<"&EDATE(A143,1)) -> 1 | D143: =SUMIFS(Events!$D$2:$D$10000,Events!$A$2:$A$10000,">="&A143,Events!$A$2:$A$10000,"<"&EDATE(A143,1)) -> 0 | E143: =SUMIFS(Events!$E$2:$E$10000,Events!$A$2:$A$10000,">="&A143,Events!$A$2:$A$10000,"<"&EDATE(A143,1)) -> 0 | F143: =SUMIFS(Events!$F$2:$F$10000,Events!$A$2:$A$10000,">="&A143,Events!$A$2:$A$10000,"<"&EDATE(A143,1)) -> 0
A144: 44501 | B144: =COUNTIFS(Events!$A$2:$A$10000,">="&A144,Events!$A$2:$A$10000,"<"&EDATE(A144,1)) -> 0 | C144: =SUMIFS(Events!$C$2:$C$10000,Events!$A$2:$A$10000,">="&A144,Events!$A$2:$A$10000,"<"&EDATE(A144,1)) -> 0 | D144: =SUMIFS(Events!$D$2:$D$10000,Events!$A$2:$A$10000,">="&A144,Events!$A$2:$A$10000,"<"&EDATE(A144,1)) -> 0 | E144: =SUMIFS(Events!$E$2:$E$10000,Events!$A$2:$A$10000,">="&A144,Events!$A$2:$A$10000,"<"&EDATE(A144,1)) -> 0 | F144: =SUMIFS(Events!$F$2:$F$10000,Events!$A$2:$A$10000,">="&A144,Events!$A$2:$A$10000,"<"&EDATE(A144,1)) -> 0
A145: 44531 | B145: =COUNTIFS(Events!$A$2:$A$10000,">="&A145,Events!$A$2:$A$10000,"<"&EDATE(A145,1)) -> 0 | C145: =SUMIFS(Events!$C$2:$C$10000,Events!$A$2:$A$10000,">="&A145,Events!$A$2:$A$10000,"<"&EDATE(A145,1)) -> 0 | D145: =SUMIFS(Events!$D$2:$D$10000,Events!$A$2:$A$10000,">="&A145,Events!$A$2:$A$10000,"<"&EDATE(A145,1)) -> 0 | E145: =SUMIFS(Events!$E$2:$E$10000,Events!$A$2:$A$10000,">="&A145,Events!$A$2:$A$10000,"<"&EDATE(A145,1)) -> 0 | F145: =SUMIFS(Events!$F$2:$F$10000,Events!$A$2:$A$10000,">="&A145,Events!$A$2:$A$10000,"<"&EDATE(A145,1)) -> 0
A146: 44562 | B146: =COUNTIFS(Events!$A$2:$A$10000,">="&A146,Events!$A$2:$A$10000,"<"&EDATE(A146,1)) -> 0 | C146: =SUMIFS(Events!$C$2:$C$10000,Events!$A$2:$A$10000,">="&A146,Events!$A$2:$A$10000,"<"&EDATE(A146,1)) -> 0 | D146: =SUMIFS(Events!$D$2:$D$10000,Events!$A$2:$A$10000,">="&A146,Events!$A$2:$A$10000,"<"&EDATE(A146,1)) -> 0 | E146: =SUMIFS(Events!$E$2:$E$10000,Events!$A$2:$A$10000,">="&A146,Events!$A$2:$A$10000,"<"&EDATE(A146,1)) -> 0 | F146: =SUMIFS(Events!$F$2:$F$10000,Events!$A$2:$A$10000,">="&A146,Events!$A$2:$A$10000,"<"&EDATE(A146,1)) -> 0
... A154: 44805 | B154: =COUNTIFS(Events!$A$2:$A$10000,">="&A154,Events!$A$2:$A$10000,"<"&EDATE(A154,1)) -> 0 | C154: =SUMIFS(Events!$C$2:$C$10000,Events!$A$2:$A$10000,">="&A154,Events!$A$2:$A$10000,"<"&EDATE(A154,1)) -> 0 | D154: =SUMIFS(Events!$D$2:$D$10000,Events!$A$2:$A$10000,">="&A154,Events!$A$2:$A$10000,"<"&EDATE(A154,1)) -> 0 | E154: =SUMIFS(Events!$E$2:$E$10000,Events!$A$2:$A$10000,">="&A154,Events!$A$2:$A$10000,"<"&EDATE(A154,1)) -> 0 | F154: =SUMIFS(Events!$F$2:$F$10000,Events!$A$2:$A$10000,">="&A154,Events!$A$2:$A$10000,"<"&EDATE(A154,1)) -> 0
A155: 44835 | B155: =COUNTIFS(Events!$A$2:$A$10000,">="&A155,Events!$A$2:$A$10000,"<"&EDATE(A155,1)) -> 0 | C155: =SUMIFS(Events!$C$2:$C$10000,Events!$A$2:$A$10000,">="&A155,Events!$A$2:$A$10000,"<"&EDATE(A155,1)) -> 0 | D155: =SUMIFS(Events!$D$2:$D$10000,Events!$A$2:$A$10000,">="&A155,Events!$A$2:$A$10000,"<"&EDATE(A155,1)) -> 0 | E155: =SUMIFS(Events!$E$2:$E$10000,Events!$A$2:$A$10000,">="&A155,Events!$A$2:$A$10000,"<"&EDATE(A155,1)) -> 0 | F155: =SUMIFS(Events!$F$2:$F$10000,Events!$A$2:$A$10000,">="&A155,Events!$A$2:$A$10000,"<"&EDATE(A155,1)) -> 0 | G155: Biden administration announces major semiconductor/export-control restrictions on China (7 Oct).
A156: 44866 | B156: =COUNTIFS(Events!$A$2:$A$10000,">="&A156,Events!$A$2:$A$10000,"<"&EDATE(A156,1)) -> 0 | C156: =SUMIFS(Events!$C$2:$C$10000,Events!$A$2:$A$10000,">="&A156,Events!$A$2:$A$10000,"<"&EDATE(A156,1)) -> 0 | D156: =SUMIFS(Events!$D$2:$D$10000,Events!$A$2:$A$10000,">="&A156,Events!$A$2:$A$10000,"<"&EDATE(A156,1)) -> 0 | E156: =SUMIFS(Events!$E$2:$E$10000,Events!$A$2:$A$10000,">="&A156,Events!$A$2:$A$10000,"<"&EDATE(A156,1)) -> 0 | F156: =SUMIFS(Events!$F$2:$F$10000,Events!$A$2:$A$10000,">="&A156,Events!$A$2:$A$10000,"<"&EDATE(A156,1)) -> 0
A157: 44896 | B157: =COUNTIFS(Events!$A$2:$A$10000,">="&A157,Events!$A$2:$A$10000,"<"&EDATE(A157,1)) -> 0 | C157: =SUMIFS(Events!$C$2:$C$10000,Events!$A$2:$A$10000,">="&A157,Events!$A$2:$A$10000,"<"&EDATE(A157,1)) -> 0 | D157: =SUMIFS(Events!$D$2:$D$10000,Events!$A$2:$A$10000,">="&A157,Events!$A$2:$A$10000,"<"&EDATE(A157,1)) -> 0 | E157: =SUMIFS(Events!$E$2:$E$10000,Events!$A$2:$A$10000,">="&A157,Events!$A$2:$A$10000,"<"&EDATE(A157,1)) -> 0 | F157: =SUMIFS(Events!$F$2:$F$10000,Events!$A$2:$A$10000,">="&A157,Events!$A$2:$A$10000,"<"&EDATE(A157,1)) -> 0
A158: 44927 | B158: =COUNTIFS(Events!$A$2:$A$10000,">="&A158,Events!$A$2:$A$10000,"<"&EDATE(A158,1)) -> 0 | C158: =SUMIFS(Events!$C$2:$C$10000,Events!$A$2:$A$10000,">="&A158,Events!$A$2:$A$10000,"<"&EDATE(A158,1)) -> 0 | D158: =SUMIFS(Events!$D$2:$D$10000,Events!$A$2:$A$10000,">="&A158,Events!$A$2:$A$10000,"<"&EDATE(A158,1)) -> 0 | E158: =SUMIFS(Events!$E$2:$E$10000,Events!$A$2:$A$10000,">="&A158,Events!$A$2:$A$10000,"<"&EDATE(A158,1)) -> 0 | F158: =SUMIFS(Events!$F$2:$F$10000,Events!$A$2:$A$10000,">="&A158,Events!$A$2:$A$10000,"<"&EDATE(A158,1)) -> 0
A159: 44958 | B159: =COUNTIFS(Events!$A$2:$A$10000,">="&A159,Events!$A$2:$A$10000,"<"&EDATE(A159,1)) -> 0 | C159: =SUMIFS(Events!$C$2:$C$10000,Events!$A$2:$A$10000,">="&A159,Events!$A$2:$A$10000,"<"&EDATE(A159,1)) -> 0 | D159: =SUMIFS(Events!$D$2:$D$10000,Events!$A$2:$A$10000,">="&A159,Events!$A$2:$A$10000,"<"&EDATE(A159,1)) -> 0 | E159: =SUMIFS(Events!$E$2:$E$10000,Events!$A$2:$A$10000,">="&A159,Events!$A$2:$A$10000,"<"&EDATE(A159,1)) -> 0 | F159: =SUMIFS(Events!$F$2:$F$10000,Events!$A$2:$A$10000,">="&A159,Events!$A$2:$A$10000,"<"&EDATE(A159,1)) -> 0
A160: 44986 | B160: =COUNTIFS(Events!$A$2:$A$10000,">="&A160,Events!$A$2:$A$10000,"<"&EDATE(A160,1)) -> 1 | C160: =SUMIFS(Events!$C$2:$C$10000,Events!$A$2:$A$10000,">="&A160,Events!$A$2:$A$10000,"<"&EDATE(A160,1)) -> 1 | D160: =SUMIFS(Events!$D$2:$D$10000,Events!$A$2:$A$10000,">="&A160,Events!$A$2:$A$10000,"<"&EDATE(A160,1)) -> 0 | E160: =SUMIFS(Events!$E$2:$E$10000,Events!$A$2:$A$10000,">="&A160,Events!$A$2:$A$10000,"<"&EDATE(A160,1)) -> 0 | F160: =SUMIFS(Events!$F$2:$F$10000,Events!$A$2:$A$10000,">="&A160,Events!$A$2:$A$10000,"<"&EDATE(A160,1)) -> 0
A161: 45017 | B161: =COUNTIFS(Events!$A$2:$A$10000,">="&A161,Events!$A$2:$A$10000,"<"&EDATE(A161,1)) -> 0 | C161: =SUMIFS(Events!$C$2:$C$10000,Events!$A$2:$A$10000,">="&A161,Events!$A$2:$A$10000,"<"&EDATE(A161,1)) -> 0 | D161: =SUMIFS(Events!$D$2:$D$10000,Events!$A$2:$A$10000,">="&A161,Events!$A$2:$A$10000,"<"&EDATE(A161,1)) -> 0 | E161: =SUMIFS(Events!$E$2:$E$10000,Events!$A$2:$A$10000,">="&A161,Events!$A$2:$A$10000,"<"&EDATE(A161,1)) -> 0 | F161: =SUMIFS(Events!$F$2:$F$10000,Events!$A$2:$A$10000,">="&A161,Events!$A$2:$A$10000,"<"&EDATE(A161,1)) -> 0
A162: 45047 | B162: =COUNTIFS(Events!$A$2:$A$10000,">="&A162,Events!$A$2:$A$10000,"<"&EDATE(A162,1)) -> 0 | C162: =SUMIFS(Events!$C$2:$C$10000,Events!$A$2:$A$10000,">="&A162,Events!$A$2:$A$10000,"<"&EDATE(A162,1)) -> 0 | D162: =SUMIFS(Events!$D$2:$D$10000,Events!$A$2:$A$10000,">="&A162,Events!$A$2:$A$10000,"<"&EDATE(A162,1)) -> 0 | E162: =SUMIFS(Events!$E$2:$E$10000,Events!$A$2:$A$10000,">="&A162,Events!$A$2:$A$10000,"<"&EDATE(A162,1)) -> 0 | F162: =SUMIFS(Events!$F$2:$F$10000,Events!$A$2:$A$10000,">="&A162,Events!$A$2:$A$10000,"<"&EDATE(A162,1)) -> 0
A163: 45078 | B163: =COUNTIFS(Events!$A$2:$A$10000,">="&A163,Events!$A$2:$A$10000,"<"&EDATE(A163,1)) -> 1 | C163: =SUMIFS(Events!$C$2:$C$10000,Events!$A$2:$A$10000,">="&A163,Events!$A$2:$A$10000,"<"&EDATE(A163,1)) -> 1 | D163: =SUMIFS(Events!$D$2:$D$10000,Events!$A$2:$A$10000,">="&A163,Events!$A$2:$A$10000,"<"&EDATE(A163,1)) -> 0 | E163: =SUMIFS(Events!$E$2:$E$10000,Events!$A$2:$A$10000,">="&A163,Events!$A$2:$A$10000,"<"&EDATE(A163,1)) -> 0 | F163: =SUMIFS(Events!$F$2:$F$10000,Events!$A$2:$A$10000,">="&A163,Events!$A$2:$A$10000,"<"&EDATE(A163,1)) -> 0 | G163: US and India announce resolution of several WTO disputes; India agrees to remove retaliatory Section 232 tariffs.
A164: 45108 | B164: =COUNTIFS(Events!$A$2:$A$10000,">="&A164,Events!$A$2:$A$10000,"<"&EDATE(A164,1)) -> 0 | C164: =SUMIFS(Events!$C$2:$C$10000,Events!$A$2:$A$10000,">="&A164,Events!$A$2:$A$10000,"<"&EDATE(A164,1)) -> 0 | D164: =SUMIFS(Events!$D$2:$D$10000,Events!$A$2:$A$10000,">="&A164,Events!$A$2:$A$10000,"<"&EDATE(A164,1)) -> 0 | E164: =SUMIFS(Events!$E$2:$E$10000,Events!$A$2:$A$10000,">="&A164,Events!$A$2:$A$10000,"<"&EDATE(A164,1)) -> 0 | F164: =SUMIFS(Events!$F$2:$F$10000,Events!$A$2:$A$10000,">="&A164,Events!$A$2:$A$10000,"<"&EDATE(A164,1)) -> 0
A165: 45139 | B165: =COUNTIFS(Events!$A$2:$A$10000,">="&A165,Events!$A$2:$A$10000,"<"&EDATE(A165,1)) -> 0 | C165: =SUMIFS(Events!$C$2:$C$10000,Events!$A$2:$A$10000,">="&A165,Events!$A$2:$A$10000,"<"&EDATE(A165,1)) -> 0 | D165: =SUMIFS(Events!$D$2:$D$10000,Events!$A$2:$A$10000,">="&A165,Events!$A$2:$A$10000,"<"&EDATE(A165,1)) -> 0 | E165: =SUMIFS(Events!$E$2:$E$10000,Events!$A$2:$A$10000,">="&A165,Events!$A$2:$A$10000,"<"&EDATE(A165,1)) -> 0 | F165: =SUMIFS(Events!$F$2:$F$10000,Events!$A$2:$A$10000,">="&A165,Events!$A$2:$A$10000,"<"&EDATE(A165,1)) -> 0
...

Sheet Annual Observations
A1: O | B1: Total events | C1: Acquiescence events | D1: Adaptation events | E1: Aggregation events | F1: Other events | G1: Acquiescence-Adaptation combined events | H1: Acquiescence-Aggregation events | I1: Acquiescence-Other events | J1: Adaptation-Aggregation events | K1: Adaptation-Other events | L1: Aggregation-Other events | M1: Year highlights
A2: 2010 | B2: =COUNTIFS(Events!$A:$A,">="&DATE($A2,1,1),Events!$A:$A,"<"&DATE($A2+1,1,1)) -> 3 | C2: =COUNTIFS(Events!$A:$A,">="&DATE($A2,1,1),Events!$A:$A,"<"&DATE($A2+1,1,1),Events!$C:$C,1) -> 2 | D2: =COUNTIFS(Events!$A:$A,">="&DATE($A2,1,1),Events!$A:$A,"<"&DATE($A2+1,1,1),Events!$D:$D,1) -> 0 | E2: =COUNTIFS(Events!$A:$A,">="&DATE($A2,1,1),Events!$A:$A,"<"&DATE($A2+1,1,1),Events!$E:$E,1) -> 0 | F2: =COUNTIFS(Events!$A:$A,">="&DATE($A2,1,1),Events!$A:$A,"<"&DATE($A2+1,1,1),Events!$F:$F,1) -> 1 | G2: =COUNTIFS(Events!$A:$A,">="&DATE($A2,1,1),Events!$A:$A,"<"&DATE($A2+1,1,1),Events!$C:$C,1,Events!$D:$D,1) -> 0 | H2: =COUNTIFS(Events!$A:$A,">="&DATE($A2,1,1),Events!$A:$A,"<"&DATE($A2+1,1,1),Events!$C:$C,1,Events!$E:$E,1) -> 0 | I2: =COUNTIFS(Events!$A:$A,">="&DATE($A2,1,1),Events!$A:$A,"<"&DATE($A2+1,1,1),Events!$C:$C,1,Events!$F:$F,1) -> 0 | J2: =COUNTIFS(Events!$A:$A,">="&DATE($A2,1,1),Events!$A:$A,"<"&DATE($A2+1,1,1),Events!$D:$D,1,Events!$E:$E,1) -> 0 | K2: =COUNTIFS(Events!$A:$A,">="&DATE($A2,1,1),Events!$A:$A,"<"&DATE($A2+1,1,1),Events!$D:$D,1,Events!$F:$F,1) -> 0 | L2: =COUNTIFS(Events!$A:$A,">="&DATE($A2,1,1),Events!$A:$A,"<"&DATE($A2+1,1,1),Events!$E:$E,1,Events!$F:$F,1) -> 0 | M2: Vietnam challenged US shrimp anti-dumping measures; South Korea made KORUS auto concessions late in the year.
A3: 2011 | B3: =COUNTIFS(Events!$A:$A,">="&DATE($A3,1,1),Events!$A:$A,"<"&DATE($A3+1,1,1)) -> 1 | C3: =COUNTIFS(Events!$A:$A,">="&DATE($A3,1,1),Events!$A:$A,"<"&DATE($A3+1,1,1),Events!$C:$C,1) -> 1 | D3: =COUNTIFS(Events!$A:$A,">="&DATE($A3,1,1),Events!$A:$A,"<"&DATE($A3+1,1,1),Events!$D:$D,1) -> 0 | E3: =COUNTIFS(Events!$A:$A,">="&DATE($A3,1,1),Events!$A:$A,"<"&DATE($A3+1,1,1),Events!$E:$E,1) -> 0 | F3: =COUNTIFS(Events!$A:$A,">="&DATE($A3,1,1),Events!$A:$A,"<"&DATE($A3+1,1,1),Events!$F:$F,1) -> 0 | G3: =COUNTIFS(Events!$A:$A,">="&DATE($A3,1,1),Events!$A:$A,"<"&DATE($A3+1,1,1),Events!$C:$C,1,Events!$D:$D,1) -> 0 | H3: =COUNTIFS(Events!$A:$A,">="&DATE($A3,1,1),Events!$A:$A,"<"&DATE($A3+1,1,1),Events!$C:$C,1,Events!$E:$E,1) -> 0 | I3: =COUNTIFS(Events!$A:$A,">="&DATE($A3,1,1),Events!$A:$A,"<"&DATE($A3+1,1,1),Events!$C:$C,1,Events!$F:$F,1) -> 0 | J3: =COUNTIFS(Events!$A:$A,">="&DATE($A3,1,1),Events!$A:$A,"<"&DATE($A3+1,1,1),Events!$D:$D,1,Events!$E:$E,1) -> 0 | K3: =COUNTIFS(Events!$A:$A,">="&DATE($A3,1,1),Events!$A:$A,"<"&DATE($A3+1,1,1),Events!$D:$D,1,Events!$F:$F,1) -> 0 | L3: =COUNTIFS(Events!$A:$A,">="&DATE($A3,1,1),Events!$A:$A,"<"&DATE($A3+1,1,1),Events!$E:$E,1,Events!$F:$F,1) -> 0 | M3: A single recorded response: Japan began reviewing restrictions on US beef after sustained US pressure.
A4: 2012 | B4: =COUNTIFS(Events!$A:$A,">="&DATE($A4,1,1),Events!$A:$A,"<"&DATE($A4+1,1,1)) -> 1 | C4: =COUNTIFS(Events!$A:$A,">="&DATE($A4,1,1),Events!$A:$A,"<"&DATE($A4+1,1,1),Events!$C:$C,1) -> 0 | D4: =COUNTIFS(Events!$A:$A,">="&DATE($A4,1,1),Events!$A:$A,"<"&DATE($A4+1,1,1),Events!$D:$D,1) -> 0 | E4: =COUNTIFS(Events!$A:$A,">="&DATE($A4,1,1),Events!$A:$A,"<"&DATE($A4+1,1,1),Events!$E:$E,1) -> 0 | F4: =COUNTIFS(Events!$A:$A,">="&DATE($A4,1,1),Events!$A:$A,"<"&DATE($A4+1,1,1),Events!$F:$F,1) -> 1 | G4: =COUNTIFS(Events!$A:$A,">="&DATE($A4,1,1),Events!$A:$A,"<"&DATE($A4+1,1,1),Events!$C:$C,1,Events!$D:$D,1) -> 0 | H4: =COUNTIFS(Events!$A:$A,">="&DATE($A4,1,1),Events!$A:$A,"<"&DATE($A4+1,1,1),Events!$C:$C,1,Events!$E:$E,1) -> 0 | I4: =COUNTIFS(Events!$A:$A,">="&DATE($A4,1,1),Events!$A:$A,"<"&DATE($A4+1,1,1),Events!$C:$C,1,Events!$F:$F,1) -> 0 | J4: =COUNTIFS(Events!$A:$A,">="&DATE($A4,1,1),Events!$A:$A,"<"&DATE($A4+1,1,1),Events!$D:$D,1,Events!$E:$E,1) -> 0 | K4: =COUNTIFS(Events!$A:$A,">="&DATE($A4,1,1),Events!$A:$A,"<"&DATE($A4+1,1,1),Events!$D:$D,1,Events!$F:$F,1) -> 0 | L4: =COUNTIFS(Events!$A:$A,">="&DATE($A4,1,1),Events!$A:$A,"<"&DATE($A4+1,1,1),Events!$E:$E,1,Events!$F:$F,1) -> 0 | M4: A single recorded response: Vietnam launched another WTO challenge to US shrimp duties.
A5: 2013 | B5: =COUNTIFS(Events!$A:$A,">="&DATE($A5,1,1),Events!$A:$A,"<"&DATE($A5+1,1,1)) -> 5 | C5: =COUNTIFS(Events!$A:$A,">="&DATE($A5,1,1),Events!$A:$A,"<"&DATE($A5+1,1,1),Events!$C:$C,1) -> 4 | D5: =COUNTIFS(Events!$A:$A,">="&DATE($A5,1,1),Events!$A:$A,"<"&DATE($A5+1,1,1),Events!$D:$D,1) -> 0 | E5: =COUNTIFS(Events!$A:$A,">="&DATE($A5,1,1),Events!$A:$A,"<"&DATE($A5+1,1,1),Events!$E:$E,1) -> 0 | F5: =COUNTIFS(Events!$A:$A,">="&DATE($A5,1,1),Events!$A:$A,"<"&DATE($A5+1,1,1),Events!$F:$F,1) -> 1 | G5: =COUNTIFS(Events!$A:$A,">="&DATE($A5,1,1),Events!$A:$A,"<"&DATE($A5+1,1,1),Events!$C:$C,1,Events!$D:$D,1) -> 0 | H5: =COUNTIFS(Events!$A:$A,">="&DATE($A5,1,1),Events!$A:$A,"<"&DATE($A5+1,1,1),Events!$C:$C,1,Events!$E:$E,1) -> 0 | I5: =COUNTIFS(Events!$A:$A,">="&DATE($A5,1,1),Events!$A:$A,"<"&DATE($A5+1,1,1),Events!$C:$C,1,Events!$F:$F,1) -> 0 | J5: =COUNTIFS(Events!$A:$A,">="&DATE($A5,1,1),Events!$A:$A,"<"&DATE($A5+1,1,1),Events!$D:$D,1,Events!$E:$E,1) -> 0 | K5: =COUNTIFS(Events!$A:$A,">="&DATE($A5,1,1),Events!$A:$A,"<"&DATE($A5+1,1,1),Events!$D:$D,1,Events!$F:$F,1) -> 0 | L5: =COUNTIFS(Events!$A:$A,">="&DATE($A5,1,1),Events!$A:$A,"<"&DATE($A5+1,1,1),Events!$E:$E,1,Events!$F:$F,1) -> 0 | M5: A broader acquiescence cluster: Japan made several TPP-entry concessions and India relaxed electronics local-purchase rules; Indonesia maintained contested import restrictions.
A6: 2014 | B6: =COUNTIFS(Events!$A:$A,">="&DATE($A6,1,1),Events!$A:$A,"<"&DATE($A6+1,1,1)) -> 2 | C6: =COUNTIFS(Events!$A:$A,">="&DATE($A6,1,1),Events!$A:$A,"<"&DATE($A6+1,1,1),Events!$C:$C,1) -> 2 | D6: =COUNTIFS(Events!$A:$A,">="&DATE($A6,1,1),Events!$A:$A,"<"&DATE($A6+1,1,1),Events!$D:$D,1) -> 0 | E6: =COUNTIFS(Events!$A:$A,">="&DATE($A6,1,1),Events!$A:$A,"<"&DATE($A6+1,1,1),Events!$E:$E,1) -> 0 | F6: =COUNTIFS(Events!$A:$A,">="&DATE($A6,1,1),Events!$A:$A,"<"&DATE($A6+1,1,1),Events!$F:$F,1) -> 0 | G6: =COUNTIFS(Events!$A:$A,">="&DATE($A6,1,1),Events!$A:$A,"<"&DATE($A6+1,1,1),Events!$C:$C,1,Events!$D:$D,1) -> 0 | H6: =COUNTIFS(Events!$A:$A,">="&DATE($A6,1,1),Events!$A:$A,"<"&DATE($A6+1,1,1),Events!$C:$C,1,Events!$E:$E,1) -> 0 | I6: =COUNTIFS(Events!$A:$A,">="&DATE($A6,1,1),Events!$A:$A,"<"&DATE($A6+1,1,1),Events!$C:$C,1,Events!$F:$F,1) -> 0 | J6: =COUNTIFS(Events!$A:$A,">="&DATE($A6,1,1),Events!$A:$A,"<"&DATE($A6+1,1,1),Events!$D:$D,1,Events!$E:$E,1) -> 0 | K6: =COUNTIFS(Events!$A:$A,">="&DATE($A6,1,1),Events!$A:$A,"<"&DATE($A6+1,1,1),Events!$D:$D,1,Events!$F:$F,1) -> 0 | L6: =COUNTIFS(Events!$A:$A,">="&DATE($A6,1,1),Events!$A:$A,"<"&DATE($A6+1,1,1),Events!$E:$E,1,Events!$F:$F,1) -> 0 | M6: Recorded activity is concentrated in the Philippines, with IP and agricultural market-access concessions.
A7: 2015 | B7: =COUNTIFS(Events!$A:$A,">="&DATE($A7,1,1),Events!$A:$A,"<"&DATE($A7+1,1,1)) -> 2 | C7: =COUNTIFS(Events!$A:$A,">="&DATE($A7,1,1),Events!$A:$A,"<"&DATE($A7+1,1,1),Events!$C:$C,1) -> 2 | D7: =COUNTIFS(Events!$A:$A,">="&DATE($A7,1,1),Events!$A:$A,"<"&DATE($A7+1,1,1),Events!$D:$D,1) -> 0 | E7: =COUNTIFS(Events!$A:$A,">="&DATE($A7,1,1),Events!$A:$A,"<"&DATE($A7+1,1,1),Events!$E:$E,1) -> 0 | F7: =COUNTIFS(Events!$A:$A,">="&DATE($A7,1,1),Events!$A:$A,"<"&DATE($A7+1,1,1),Events!$F:$F,1) -> 0 | G7: =COUNTIFS(Events!$A:$A,">="&DATE($A7,1,1),Events!$A:$A,"<"&DATE($A7+1,1,1),Events!$C:$C,1,Events!$D:$D,1) -> 0 | H7: =COUNTIFS(Events!$A:$A,">="&DATE($A7,1,1),Events!$A:$A,"<"&DATE($A7+1,1,1),Events!$C:$C,1,Events!$E:$E,1) -> 0 | I7: =COUNTIFS(Events!$A:$A,">="&DATE($A7,1,1),Events!$A:$A,"<"&DATE($A7+1,1,1),Events!$C:$C,1,Events!$F:$F,1) -> 0 | J7: =COUNTIFS(Events!$A:$A,">="&DATE($A7,1,1),Events!$A:$A,"<"&DATE($A7+1,1,1),Events!$D:$D,1,Events!$E:$E,1) -> 0 | K7: =COUNTIFS(Events!$A:$A,">="&DATE($A7,1,1),Events!$A:$A,"<"&DATE($A7+1,1,1),Events!$D:$D,1,Events!$F:$F,1) -> 0 | L7: =COUNTIFS(Events!$A:$A,">="&DATE($A7,1,1),Events!$A:$A,"<"&DATE($A7+1,1,1),Events!$E:$E,1,Events!$F:$F,1) -> 0 | M7: India committed to implement the adverse poultry ruling; Philippine reforms led the US to close its GSP worker-rights review.
A8: 2016 | B8: =COUNTIFS(Events!$A:$A,">="&DATE($A8,1,1),Events!$A:$A,"<"&DATE($A8+1,1,1)) -> 7 | C8: =COUNTIFS(Events!$A:$A,">="&DATE($A8,1,1),Events!$A:$A,"<"&DATE($A8+1,1,1),Events!$C:$C,1) -> 5 | D8: =COUNTIFS(Events!$A:$A,">="&DATE($A8,1,1),Events!$A:$A,"<"&DATE($A8+1,1,1),Events!$D:$D,1) -> 0 | E8: =COUNTIFS(Events!$A:$A,">="&DATE($A8,1,1),Events!$A:$A,"<"&DATE($A8+1,1,1),Events!$E:$E,1) -> 0 | F8: =COUNTIFS(Events!$A:$A,">="&DATE($A8,1,1),Events!$A:$A,"<"&DATE($A8+1,1,1),Events!$F:$F,1) -> 2 | G8: =COUNTIFS(Events!$A:$A,">="&DATE($A8,1,1),Events!$A:$A,"<"&DATE($A8+1,1,1),Events!$C:$C,1,Events!$D:$D,1) -> 0 | H8: =COUNTIFS(Events!$A:$A,">="&DATE($A8,1,1),Events!$A:$A,"<"&DATE($A8+1,1,1),Events!$C:$C,1,Events!$E:$E,1) -> 0 | I8: =COUNTIFS(Events!$A:$A,">="&DATE($A8,1,1),Events!$A:$A,"<"&DATE($A8+1,1,1),Events!$C:$C,1,Events!$F:$F,1) -> 0 | J8: =COUNTIFS(Events!$A:$A,">="&DATE($A8,1,1),Events!$A:$A,"<"&DATE($A8+1,1,1),Events!$D:$D,1,Events!$E:$E,1) -> 0 | K8: =COUNTIFS(Events!$A:$A,">="&DATE($A8,1,1),Events!$A:$A,"<"&DATE($A8+1,1,1),Events!$D:$D,1,Events!$F:$F,1) -> 0 | L8: =COUNTIFS(Events!$A:$A,">="&DATE($A8,1,1),Events!$A:$A,"<"&DATE($A8+1,1,1),Events!$E:$E,1,Events!$F:$F,1) -> 0 | M8: Pre-TPP implementation and WTO disputes dominate: Malaysia and Vietnam undertook TPP-related reforms while India both contested solar rules and implemented poultry changes.
A9: 2017 | B9: =COUNTIFS(Events!$A:$A,">="&DATE($A9,1,1),Events!$A:$A,"<"&DATE($A9+1,1,1)) -> 1 | C9: =COUNTIFS(Events!$A:$A,">="&DATE($A9,1,1),Events!$A:$A,"<"&DATE($A9+1,1,1),Events!$C:$C,1) -> 0 | D9: =COUNTIFS(Events!$A:$A,">="&DATE($A9,1,1),Events!$A:$A,"<"&DATE($A9+1,1,1),Events!$D:$D,1) -> 0 | E9: =COUNTIFS(Events!$A:$A,">="&DATE($A9,1,1),Events!$A:$A,"<"&DATE($A9+1,1,1),Events!$E:$E,1) -> 0 | F9: =COUNTIFS(Events!$A:$A,">="&DATE($A9,1,1),Events!$A:$A,"<"&DATE($A9+1,1,1),Events!$F:$F,1) -> 1 | G9: =COUNTIFS(Events!$A:$A,">="&DATE($A9,1,1),Events!$A:$A,"<"&DATE($A9+1,1,1),Events!$C:$C,1,Events!$D:$D,1) -> 0 | H9: =COUNTIFS(Events!$A:$A,">="&DATE($A9,1,1),Events!$A:$A,"<"&DATE($A9+1,1,1),Events!$C:$C,1,Events!$E:$E,1) -> 0 | I9: =COUNTIFS(Events!$A:$A,">="&DATE($A9,1,1),Events!$A:$A,"<"&DATE($A9+1,1,1),Events!$C:$C,1,Events!$F:$F,1) -> 0 | J9: =COUNTIFS(Events!$A:$A,">="&DATE($A9,1,1),Events!$A:$A,"<"&DATE($A9+1,1,1),Events!$D:$D,1,Events!$E:$E,1) -> 0 | K9: =COUNTIFS(Events!$A:$A,">="&DATE($A9,1,1),Events!$A:$A,"<"&DATE($A9+1,1,1),Events!$D:$D,1,Events!$F:$F,1) -> 0 | L9: =COUNTIFS(Events!$A:$A,">="&DATE($A9,1,1),Events!$A:$A,"<"&DATE($A9+1,1,1),Events!$E:$E,1,Events!$F:$F,1) -> 0 | M9: Only one recorded event: Japan initially rejected proceeding with TPP without the United States.
A10: 2018 | B10: =COUNTIFS(Events!$A:$A,">="&DATE($A10,1,1),Events!$A:$A,"<"&DATE($A10+1,1,1)) -> 6 | C10: =COUNTIFS(Events!$A:$A,">="&DATE($A10,1,1),Events!$A:$A,"<"&DATE($A10+1,1,1),Events!$C:$C,1) -> 3 | D10: =COUNTIFS(Events!$A:$A,">="&DATE($A10,1,1),Events!$A:$A,"<"&DATE($A10+1,1,1),Events!$D:$D,1) -> 0 | E10: =COUNTIFS(Events!$A:$A,">="&DATE($A10,1,1),Events!$A:$A,"<"&DATE($A10+1,1,1),Events!$E:$E,1) -> 2 | F10: =COUNTIFS(Events!$A:$A,">="&DATE($A10,1,1),Events!$A:$A,"<"&DATE($A10+1,1,1),Events!$F:$F,1) -> 1 | G10: =COUNTIFS(Events!$A:$A,">="&DATE($A10,1,1),Events!$A:$A,"<"&DATE($A10+1,1,1),Events!$C:$C,1,Events!$D:$D,1) -> 0 | H10: =COUNTIFS(Events!$A:$A,">="&DATE($A10,1,1),Events!$A:$A,"<"&DATE($A10+1,1,1),Events!$C:$C,1,Events!$E:$E,1) -> 0 | I10: =COUNTIFS(Events!$A:$A,">="&DATE($A10,1,1),Events!$A:$A,"<"&DATE($A10+1,1,1),Events!$C:$C,1,Events!$F:$F,1) -> 0 | J10: =COUNTIFS(Events!$A:$A,">="&DATE($A10,1,1),Events!$A:$A,"<"&DATE($A10+1,1,1),Events!$D:$D,1,Events!$E:$E,1) -> 0 | K10: =COUNTIFS(Events!$A:$A,">="&DATE($A10,1,1),Events!$A:$A,"<"&DATE($A10+1,1,1),Events!$D:$D,1,Events!$F:$F,1) -> 0 | L10: =COUNTIFS(Events!$A:$A,">="&DATE($A10,1,1),Events!$A:$A,"<"&DATE($A10+1,1,1),Events!$E:$E,1,Events!$F:$F,1) -> 0 | M10: Trump-era activity broadens: CPTPP proceeds without the US and Japan-EU deepen trade ties, while South Korea and Australia negotiate or contest US trade measures.
A11: 2019 | B11: =COUNTIFS(Events!$A:$A,">="&DATE($A11,1,1),Events!$A:$A,"<"&DATE($A11+1,1,1)) -> 1 | C11: =COUNTIFS(Events!$A:$A,">="&DATE($A11,1,1),Events!$A:$A,"<"&DATE($A11+1,1,1),Events!$C:$C,1) -> 0 | D11: =COUNTIFS(Events!$A:$A,">="&DATE($A11,1,1),Events!$A:$A,"<"&DATE($A11+1,1,1),Events!$D:$D,1) -> 0 | E11: =COUNTIFS(Events!$A:$A,">="&DATE($A11,1,1),Events!$A:$A,"<"&DATE($A11+1,1,1),Events!$E:$E,1) -> 0 | F11: =COUNTIFS(Events!$A:$A,">="&DATE($A11,1,1),Events!$A:$A,"<"&DATE($A11+1,1,1),Events!$F:$F,1) -> 1 | G11: =COUNTIFS(Events!$A:$A,">="&DATE($A11,1,1),Events!$A:$A,"<"&DATE($A11+1,1,1),Events!$C:$C,1,Events!$D:$D,1) -> 0 | H11: =COUNTIFS(Events!$A:$A,">="&DATE($A11,1,1),Events!$A:$A,"<"&DATE($A11+1,1,1),Events!$C:$C,1,Events!$E:$E,1) -> 0 | I11: =COUNTIFS(Events!$A:$A,">="&DATE($A11,1,1),Events!$A:$A,"<"&DATE($A11+1,1,1),Events!$C:$C,1,Events!$F:$F,1) -> 0 | J11: =COUNTIFS(Events!$A:$A,">="&DATE($A11,1,1),Events!$A:$A,"<"&DATE($A11+1,1,1),Events!$D:$D,1,Events!$E:$E,1) -> 0 | K11: =COUNTIFS(Events!$A:$A,">="&DATE($A11,1,1),Events!$A:$A,"<"&DATE($A11+1,1,1),Events!$D:$D,1,Events!$F:$F,1) -> 0 | L11: =COUNTIFS(Events!$A:$A,">="&DATE($A11,1,1),Events!$A:$A,"<"&DATE($A11+1,1,1),Events!$E:$E,1,Events!$F:$F,1) -> 0 | M11: Only one recorded event: India retaliated against US Section 232 tariffs.
A12: 2020 | B12: =COUNTIFS(Events!$A:$A,">="&DATE($A12,1,1),Events!$A:$A,"<"&DATE($A12+1,1,1)) -> 4 | C12: =COUNTIFS(Events!$A:$A,">="&DATE($A12,1,1),Events!$A:$A,"<"&DATE($A12+1,1,1),Events!$C:$C,1) -> 3 | D12: =COUNTIFS(Events!$A:$A,">="&DATE($A12,1,1),Events!$A:$A,"<"&DATE($A12+1,1,1),Events!$D:$D,1) -> 0 | E12: =COUNTIFS(Events!$A:$A,">="&DATE($A12,1,1),Events!$A:$A,"<"&DATE($A12+1,1,1),Events!$E:$E,1) -> 1 | F12: =COUNTIFS(Events!$A:$A,">="&DATE($A12,1,1),Events!$A:$A,"<"&DATE($A12+1,1,1),Events!$F:$F,1) -> 0 | G12: =COUNTIFS(Events!$A:$A,">="&DATE($A12,1,1),Events!$A:$A,"<"&DATE($A12+1,1,1),Events!$C:$C,1,Events!$D:$D,1) -> 0 | H12: =COUNTIFS(Events!$A:$A,">="&DATE($A12,1,1),Events!$A:$A,"<"&DATE($A12+1,1,1),Events!$C:$C,1,Events!$E:$E,1) -> 0 | I12: =COUNTIFS(Events!$A:$A,">="&DATE($A12,1,1),Events!$A:$A,"<"&DATE($A12+1,1,1),Events!$C:$C,1,Events!$F:$F,1) -> 0 | J12: =COUNTIFS(Events!$A:$A,">="&DATE($A12,1,1),Events!$A:$A,"<"&DATE($A12+1,1,1),Events!$D:$D,1,Events!$E:$E,1) -> 0 | K12: =COUNTIFS(Events!$A:$A,">="&DATE($A12,1,1),Events!$A:$A,"<"&DATE($A12+1,1,1),Events!$D:$D,1,Events!$F:$F,1) -> 0 | L12: =COUNTIFS(Events!$A:$A,">="&DATE($A12,1,1),Events!$A:$A,"<"&DATE($A12+1,1,1),Events!$E:$E,1,Events!$F:$F,1) -> 0 | M12: Indonesia made several GSP-related concessions; RCEP signing supplies the principal aggregation event.
A13: 2021 | B13: =COUNTIFS(Events!$A:$A,">="&DATE($A13,1,1),Events!$A:$A,"<"&DATE($A13+1,1,1)) -> 3 | C13: =COUNTIFS(Events!$A:$A,">="&DATE($A13,1,1),Events!$A:$A,"<"&DATE($A13+1,1,1),Events!$C:$C,1) -> 3 | D13: =COUNTIFS(Events!$A:$A,">="&DATE($A13,1,1),Events!$A:$A,"<"&DATE($A13+1,1,1),Events!$D:$D,1) -> 0 | E13: =COUNTIFS(Events!$A:$A,">="&DATE($A13,1,1),Events!$A:$A,"<"&DATE($A13+1,1,1),Events!$E:$E,1) -> 0 | F13: =COUNTIFS(Events!$A:$A,">="&DATE($A13,1,1),Events!$A:$A,"<"&DATE($A13+1,1,1),Events!$F:$F,1) -> 0 | G13: =COUNTIFS(Events!$A:$A,">="&DATE($A13,1,1),Events!$A:$A,"<"&DATE($A13+1,1,1),Events!$C:$C,1,Events!$D:$D,1) -> 0 | H13: =COUNTIFS(Events!$A:$A,">="&DATE($A13,1,1),Events!$A:$A,"<"&DATE($A13+1,1,1),Events!$C:$C,1,Events!$E:$E,1) -> 0 | I13: =COUNTIFS(Events!$A:$A,">="&DATE($A13,1,1),Events!$A:$A,"<"&DATE($A13+1,1,1),Events!$C:$C,1,Events!$F:$F,1) -> 0 | J13: =COUNTIFS(Events!$A:$A,">="&DATE($A13,1,1),Events!$A:$A,"<"&DATE($A13+1,1,1),Events!$D:$D,1,Events!$E:$E,1) -> 0 | K13: =COUNTIFS(Events!$A:$A,">="&DATE($A13,1,1),Events!$A:$A,"<"&DATE($A13+1,1,1),Events!$D:$D,1,Events!$F:$F,1) -> 0 | L13: =COUNTIFS(Events!$A:$A,">="&DATE($A13,1,1),Events!$A:$A,"<"&DATE($A13+1,1,1),Events!$E:$E,1,Events!$F:$F,1) -> 0 | M13: Recorded responses are concentrated in Vietnam, with currency and timber commitments resolving or managing US Section 301 concerns.
... A18: 2026 | B18: =COUNTIFS(Events!$A:$A,">="&DATE($A18,1,1),Events!$A:$A,"<"&DATE($A18+1,1,1)) -> 4 | C18: =COUNTIFS(Events!$A:$A,">="&DATE($A18,1,1),Events!$A:$A,"<"&DATE($A18+1,1,1),Events!$C:$C,1) -> 2 | D18: =COUNTIFS(Events!$A:$A,">="&DATE($A18,1,1),Events!$A:$A,"<"&DATE($A18+1,1,1),Events!$D:$D,1) -> 2 | E18: =COUNTIFS(Events!$A:$A,">="&DATE($A18,1,1),Events!$A:$A,"<"&DATE($A18+1,1,1),Events!$E:$E,1) -> 0 | F18: =COUNTIFS(Events!$A:$A,">="&DATE($A18,1,1),Events!$A:$A,"<"&DATE($A18+1,1,1),Events!$F:$F,1) -> 1 | G18: =COUNTIFS(Events!$A:$A,">="&DATE($A18,1,1),Events!$A:$A,"<"&DATE($A18+1,1,1),Events!$C:$C,1,Events!$D:$D,1) -> 1 | H18: =COUNTIFS(Events!$A:$A,">="&DATE($A18,1,1),Events!$A:$A,"<"&DATE($A18+1,1,1),Events!$C:$C,1,Events!$E:$E,1) -> 0 | I18: =COUNTIFS(Events!$A:$A,">="&DATE($A18,1,1),Events!$A:$A,"<"&DATE($A18+1,1,1),Events!$C:$C,1,Events!$F:$F,1) -> 0 | J18: =COUNTIFS(Events!$A:$A,">="&DATE($A18,1,1),Events!$A:$A,"<"&DATE($A18+1,1,1),Events!$D:$D,1,Events!$E:$E,1) -> 0 | K18: =COUNTIFS(Events!$A:$A,">="&DATE($A18,1,1),Events!$A:$A,"<"&DATE($A18+1,1,1),Events!$D:$D,1,Events!$F:$F,1) -> 0 | L18: =COUNTIFS(Events!$A:$A,">="&DATE($A18,1,1),Events!$A:$A,"<"&DATE($A18+1,1,1),Events!$E:$E,1,Events!$F:$F,1) -> 0 | M18: Early-year sample combines India tariff concessions, South Korean domestic adaptation, and Indonesian contestation of a USTR investigation.
